{"nodes": [{"id": "2KXZIYTT"}, {"id": "NHG4G4L4"}, {"id": "EG5CF9XD"}, {"id": "CDEE3MMB"}, {"id": "7CIQ9LTV"}, {"id": "VK7MYWPG"}, {"id": "EAMLK3Y5"}, {"id": "JQNL2KII"}, {"id": "U68LQ887"}, {"id": "3SN7EBSL"}, {"id": "ICIN6V7I"}, {"id": "3ETZFFNS"}, {"id": "GJ4QZKTS"}, {"id": "XSVIIP5L"}, {"id": "GSRCBWKB"}, {"id": "ZBR2P2MG"}, {"id": "Q225KNMF"}, {"id": "83CAPN4G"}, {"id": "NEBJ85H3"}, {"id": "RS5DBPDD"}, {"id": "7QGFCBNH"}, {"id": "NN8RWTJN"}, {"id": "AN4VBEKF"}, {"id": "EJENTABB"}, {"id": "LN8M5Y5R"}, {"id": "32CEIHQE"}, {"id": "KRL6I8BU"}, {"id": "7WSWWYHM"}, {"id": "A6HRG4JG"}, {"id": "XRBM2DC8"}, {"id": "3N9XWYFJ"}, {"id": "5E5QUP9L"}, {"id": "VFE2E59A"}, {"id": "YLP38A4R"}, {"id": "DDERN2U3"}, {"id": "DN3YBFQM"}, {"id": "TR6PDBUB"}, {"id": "V4RID8TN"}, {"id": "YGSP98R9"}, {"id": "4VVW4E7R"}, {"id": "6H2ECTR5"}, {"id": "LJZB6MTP"}, {"id": "DXGRXYA2"}, {"id": "ZPB288VA"}, {"id": "FQTXYHMF"}, {"id": "RMQ3FCG9"}, {"id": "YE8B4L3K"}, {"id": "P72B2DSD"}, {"id": "FM9IYRTX"}, {"id": "UMVINAGY"}, {"id": "AD25IKQR"}, {"id": "DNXZWQYC"}, {"id": "WR44SNW8"}, {"id": "5UEP6FJF"}, {"id": "2WFBYTCC"}, {"id": "9H25VNYG"}, {"id": "9ELBEP7C"}, {"id": "MRQB7B6N"}, {"id": "LG3FSWHQ"}, {"id": "TCSF3QRJ"}, {"id": "IBSKB9AS"}, {"id": "GPPFNCKA"}, {"id": "QCGLBTNH"}, {"id": "2XPA8DN6"}, {"id": "5ARGAXD5"}, {"id": "EFF5GF65"}, {"id": "5TS8QK22"}, {"id": "PY7VZARY"}, {"id": "SFKG795G"}, {"id": "TD9CJZTL"}, {"id": "G73KS8UQ"}, {"id": "9BKHBAKQ"}, {"id": "IPC36S5V"}, {"id": "TXWCP8I8"}, {"id": "ZRBMFYZM"}, {"id": "ELW3I7GH"}, {"id": "Q7HDXF92"}, {"id": "E4ZYMDJZ"}, {"id": "NMVTYI5T"}, {"id": "MMP7ENHA"}, {"id": "GFPD6PFR"}, {"id": "FEA27PZK"}, {"id": "66UW8D43"}, {"id": "C3II3FX6"}, {"id": "YETHSI88"}, {"id": "2MJK8MHP"}, {"id": "S68H9QBG"}, {"id": "WVU5AFQJ"}, {"id": "7SQSUAJJ"}, {"id": "LCJ7JX6X"}, {"id": "6Q6LWBNP"}, {"id": "B6876BD4"}, {"id": "IKKZ8UA9"}, {"id": "DVT2R32N"}, {"id": "MBUJ4A4F"}, {"id": "GVLDYG9U"}, {"id": "6FLUSZNW"}, {"id": "9TFDXLXF"}, {"id": "5G4IZVQ8"}, {"id": "LFLTWJAM"}, {"id": "RTTHJN6V"}, {"id": "TWSMZCW6"}, {"id": "6QHZ3LJG"}, {"id": "34G9QI8T"}, {"id": "93EJ6DH8"}, {"id": "I5GW9TLE"}, {"id": "NX46SKFP"}, {"id": "YKC69FSL"}, {"id": "7L8LVZG6"}, {"id": "HL2YSKU9"}, {"id": "A4ZPDKMT"}, {"id": "CC5FSKP9"}, {"id": "98CK7UFR"}, {"id": "A3KYE8IS"}, {"id": "TC9VUUIV"}, {"id": "W7IDCXT4"}, {"id": "2CGJFSN3"}, {"id": "ELI78EZX"}, {"id": "U8JKUGA8"}, {"id": "MYBFDHFH"}, {"id": "2CAC6487"}, {"id": "WKK56EXU"}, {"id": "F9HV5EF8"}, {"id": "HLGK973Q"}, {"id": "HYTH7KQ5"}, {"id": "M8IEXC3J"}, {"id": "KGY9T3MH"}, {"id": "EXE29BH4"}, {"id": "J7JUTEAB"}, {"id": "QU7MV362"}, {"id": "Q3LGUB6S"}, {"id": "GJHWZHKJ"}, {"id": "B6CEU5DC"}, {"id": "LMIEMA55"}, {"id": "JW4WDRBE"}, {"id": "U28W6G7H"}, {"id": "ZBCN7AQW"}, {"id": "37DD97CJ"}, {"id": "AJ6Q3HEV"}, {"id": "DSQIERIF"}, {"id": "GPFCVH4W"}, {"id": "692FHSHH"}, {"id": "F7ZF6LU6"}, {"id": "PKYAFZ33"}, {"id": "235TMJP4"}, {"id": "TIPI8I2W"}, {"id": "V8SPNVP5"}, {"id": "CH2I4QZD"}, {"id": "66NTNCWL"}, {"id": "R2R8K52A"}, {"id": "L7J4LN4B"}, {"id": "97Z5KABU"}, {"id": "3UYN3NA3"}, {"id": "C2C72RPF"}, {"id": "RPTF5C6P"}, {"id": "Z7W3DR4J"}, {"id": "ZTDFG5IT"}, {"id": "VWBGJGAL"}, {"id": "KTXFLPM3"}, {"id": "797YFL9B"}, {"id": "9XMFRZKL"}, {"id": "6PCTX6BW"}, {"id": "AYBC8NT2"}, {"id": "B84VKLW9"}, {"id": "MYJM3I6X"}, {"id": "I55QRACV"}, {"id": "UIL72SAR"}, {"id": "BE48TX2H"}, {"id": "5ZFM6G5S"}, {"id": "Q586T6MR"}, {"id": "AKJLN7GG"}, {"id": "2I4CNINN"}, {"id": "5XDSJYDQ"}, {"id": "FTIE73TX"}, {"id": "B7LHX58X"}, {"id": "QGBJAIEI"}, {"id": "8VJLICRZ"}, {"id": "9ADQIL25"}, {"id": "YQ7GHGC3"}, {"id": "XLH4GHSA"}, {"id": "GJK38T9U"}, {"id": "H4FC77LT"}, {"id": "A9Z3IL6G"}, {"id": "ILEWWFTT"}, {"id": "DFHWY9KT"}, {"id": "HA9SMVE4"}, {"id": "7UWQD2V7"}, {"id": "HFV4ZKWJ"}, {"id": "5PSQ97GL"}, {"id": "NV5PBDVV"}, {"id": "4VSAZ6YN"}, {"id": "4K9QM67N"}, {"id": "YQWKSHX5"}, {"id": "9EEKDMCQ"}, {"id": "KKPRRYF5"}, {"id": "5J8BBLUH"}, {"id": "EHMGQ9UD"}, {"id": "JF88W22K"}, {"id": "UD9ELGDZ"}, {"id": "ZYA68N2R"}, {"id": "GU755I44"}, {"id": "JCSVCM3Q"}, {"id": "CEDN8EB5"}, {"id": "3SSXIPXK"}, {"id": "9M6RQUA9"}, {"id": "RZQZTZRG"}, {"id": "W6FQ3KJ5"}, {"id": "Z8I3GF4V"}, {"id": "VXZIU84M"}, {"id": "KV8PHWTV"}, {"id": "Q473REEE"}, {"id": "BHE2434I"}, {"id": "ULBJ2U9F"}, {"id": "3MS4DDA9"}, {"id": "4DHQNXK9"}, {"id": "3K8QPXKB"}, {"id": "HME9T53M"}, {"id": "W3N99HTI"}, {"id": "3V2PBUQN"}, {"id": "WRS4B94R"}, {"id": "RXLKGNDV"}, {"id": "9Z7L9INV"}, {"id": "WPVJ7BMX"}, {"id": "YKFJBKEF"}, {"id": "RC5KRZCD"}, {"id": "ERW4A5K3"}, {"id": "UMG9ZHNR"}, {"id": "HRRMJZ7P"}, {"id": "6XE6BCA9"}, {"id": "528XYVYW"}, {"id": "7NYCPT65"}, {"id": "NZ9HRJ7K"}, {"id": "DJK49L3D"}, {"id": "L4A8867M"}, {"id": "8B66GEM2"}, {"id": "D3IMH8QU"}, {"id": "PWF27R38"}, {"id": "3CK55IK5"}, {"id": "EXM5QBAL"}, {"id": "4595RUZ3"}, {"id": "2Q7TUF99"}, {"id": "2TYDU7YN"}, {"id": "NMIGKYKL"}, {"id": "8B8M8IIT"}, {"id": "8M42693P"}, {"id": "JJMULJ8U"}, {"id": "J6X9FA8M"}, {"id": "MDBVTAH7"}, {"id": "ARDEEPXR"}, {"id": "NL9QRJ8A"}, {"id": "33CHN65F"}, {"id": "IZKMXT27"}, {"id": "FXISQ7ZW"}, {"id": "KB955BFR"}, {"id": "NVG3SRJ4"}, {"id": "WZNRVQ38"}, {"id": "TZGEUNEC"}, {"id": "NA5JTD78"}, {"id": "CWKWIWG4"}, {"id": "J9WNBL8A"}, {"id": "7LPQ6DBD"}, {"id": "MFG9C974"}, {"id": "M3MI9IHT"}, {"id": "WWUJEPEZ"}, {"id": "7P4X3G4E"}, {"id": "7MYBEEJL"}, {"id": "63SCT62K"}, {"id": "AGD66LJC"}, {"id": "Y2Y2RI89"}, {"id": "NB7I59CD"}, {"id": "EJDM67E3"}, {"id": "C4J4FFM6"}, {"id": "D7DMRPV2"}, {"id": "NA83BBQ9"}, {"id": "IIM9QZV9"}, {"id": "EWUU64GR"}, {"id": "5NAEA23U"}, {"id": "I9WRBFTN"}, {"id": "SHZBLVNX"}, {"id": "EXENA72Y"}, {"id": "HS2MRUCX"}, {"id": "AUQ4TB89"}, {"id": "MSXD2NSV"}, {"id": "PN4KZW88"}, {"id": "ASVT2FM6"}, {"id": "UW3MAL32"}, {"id": "7VHGUCIE"}, {"id": "UAW9VMWX"}, {"id": "QRCNLMFC"}, {"id": "XH9L2QDC"}, {"id": "I8XV7B38"}, {"id": "564YS9JY"}, {"id": "XI7CYRG8"}, {"id": "N9CJVIAZ"}, {"id": "3IKXM4X7"}, {"id": "XB78ZGFK"}, {"id": "7N4BYR84"}, {"id": "37QKRIYC"}, {"id": "2LDNCRN4"}, {"id": "F9VLX7PS"}, {"id": "Y4DL944F"}, {"id": "Z52SMZ9I"}, {"id": "NTUWGCDT"}, {"id": "67IANJIE"}, {"id": "NNCPUHE6"}, {"id": "VZK6BF78"}, {"id": "EI2PAMBG"}, {"id": "9G5KE3NB"}, {"id": "JHITWF3L"}, {"id": "2Q4HVPUJ"}, {"id": "IDI6S8GS"}, {"id": "3K2FESNS"}, {"id": "THS8SVYY"}, {"id": "KGZ6UCQL"}, {"id": "LIBVLLA2"}, {"id": "CTE2JETU"}, {"id": "VTK2L8MK"}, {"id": "CN8X5IJB"}, {"id": "74K4782Q"}, {"id": "E5UC3428"}, {"id": "YGRIWHW4"}, {"id": "UULVBDSB"}, {"id": "8FRVH3NK"}, {"id": "H9U8VET3"}, {"id": "NDBBXSFX"}, {"id": "QNEKP2L8"}, {"id": "NEY2LB77"}, {"id": "RJF67ZIL"}, {"id": "FHXYQJ5A"}, {"id": "QIAUJG5Q"}, {"id": "DJRSCTXM"}, {"id": "R5QFW2RA"}, {"id": "N8IBRSYQ"}, {"id": "AHUR6D8V"}, {"id": "ADBR8XLT"}, {"id": "7QKHXR48"}, {"id": "F2L78HEX"}, {"id": "L8NXQD2H"}, {"id": "6SUNA9ZC"}, {"id": "AIHUXYD5"}, {"id": "MAXAKMU3"}, {"id": "VR4FDYCU"}, {"id": "97Q2YYXG"}, {"id": "ZVE482RF"}, {"id": "636EBTU9"}, {"id": "FE8FP9D7"}, {"id": "NVKR6U7A"}, {"id": "SBR8JG4H"}, {"id": "42IDCQHX"}, {"id": "LXMLAZEY"}, {"id": "3FP23RSV"}, {"id": "YS4B79SA"}, {"id": "4LX92JX4"}, {"id": "Y5JVH5WE"}, {"id": "7GJ3IZ6V"}, {"id": "GTTJ59J6"}, {"id": "N7T4ZT8C"}, {"id": "VEVPRU6Q"}, {"id": "CXAL64XJ"}, {"id": "ZTIJEPMW"}, {"id": "DXXKQ7T9"}, {"id": "8HFVN58A"}, {"id": "DPYVT2TP"}, {"id": "5Z3LQNLZ"}, {"id": "VQNTBV95"}, {"id": "L8NRCZ8E"}, {"id": "C6YPQLJI"}, {"id": "75IT43QT"}, {"id": "ZPTC2EU2"}, {"id": "7UEWRDBF"}, {"id": "LKW5ARUX"}, {"id": "IJFUF9XC"}, {"id": "DXJZBZW7"}, {"id": "DGWGMJ7U"}, {"id": "YH8A2UHK"}, {"id": "BMHCIT94"}, {"id": "298BNUC8"}, {"id": "MJUHEIIH"}, {"id": "2DAFRDMY"}, {"id": "J3BRZ59N"}, {"id": "9FY2LAJF"}, {"id": "YNKK75LQ"}, {"id": "CUW3YJPW"}, {"id": "ICGJ5R6J"}, {"id": "BG32MCY5"}, {"id": "Z8YNTPTS"}, {"id": "6E5KLX6X"}, {"id": "U8TX647F"}, {"id": "REGGRY8M"}, {"id": "CNHW6H66"}, {"id": "4E4DALCD"}, {"id": "WXVT9IWS"}, {"id": "B7FRA7CR"}, {"id": "YRG6ESN4"}, {"id": "PSKGU9XR"}, {"id": "8FV8H8WB"}, {"id": "874N6QHD"}, {"id": "3YI7DFW2"}, {"id": "PJN6ACVA"}, {"id": "8J6EQLST"}, {"id": "LBRII9F5"}, {"id": "Z4KN26RY"}, {"id": "PR2LV2XL"}, {"id": "2CCB2DFF"}, {"id": "AR2BHG9K"}, {"id": "C44N7NAR"}, {"id": "WD6EIVIV"}, {"id": "U2ZWMF5Q"}, {"id": "FZAUK87U"}, {"id": "XB6ES2CL"}, {"id": "EFJYEVC6"}, {"id": "LS3DVSRL"}, {"id": "YELA7MTZ"}, {"id": "Z9KG6CD6"}, {"id": "XH58TNLL"}, {"id": "AEQHK3PN"}, {"id": "V37PB4KM"}, {"id": "3RP9NCHT"}, {"id": "S9VWQ4SW"}, {"id": "VDBZSK5N"}, {"id": "9D6RLLGK"}, {"id": "I95YCTJ8"}, {"id": "4I95LEVG"}, {"id": "4RC9LPI4"}, {"id": "7PEDCTSP"}, {"id": "84BTZRXE"}, {"id": "LG56XJV4"}, {"id": "43VL8TVM"}, {"id": "IK5VV9S6"}, {"id": "H4D56SJW"}, {"id": "JMBH9DZ3"}, {"id": "YVNDG5GA"}, {"id": "9W67N3W2"}, {"id": "T2QMJHUW"}, {"id": "TF258FMY"}, {"id": "GMXY7BWK"}, {"id": "VJ66H9QC"}, {"id": "BLZ4M3Y4"}, {"id": "EBUAS4W8"}, {"id": "3CP5KRDI"}, {"id": "TJM5C3QJ"}, {"id": "LWR2AXGE"}, {"id": "7QK5BNAN"}, {"id": "T4KFKLRI"}, {"id": "GPTDRNJR"}, {"id": "LRZJZVPL"}, {"id": "8SCKG23G"}, {"id": "F89Z26U4"}, {"id": "PPRISUKF"}, {"id": "DM8JRXL3"}, {"id": "TRN2VFVL"}, {"id": "GJ9R7DKV"}, {"id": "4SHNAL4U"}, {"id": "RNI76T8X"}, {"id": "3S7J23W4"}, {"id": "5XYEWJ56"}, {"id": "26B4JXMQ"}, {"id": "5JHNYD2W"}, {"id": "TCRGLTG2"}, {"id": "IXZCFH88"}, {"id": "HEN6HS4C"}, {"id": "9U7CKEUD"}, {"id": "XKFR78UH"}, {"id": "4YVM9SWB"}, {"id": "XG33BSQ4"}, {"id": "EM9JCYAZ"}, {"id": "H3LYYGZ8"}, {"id": "J5FFLRYZ"}, {"id": "RV42EVAU"}, {"id": "TU2VIQQY"}, {"id": "RJRWMPZC"}, {"id": "U698CFBR"}, {"id": "2FF2WT72"}, {"id": "A5GC3I4X"}, {"id": "STVECQYK"}, {"id": "8EZM6ZYV"}, {"id": "QM5ZNYQN"}, {"id": "6BV8YS95"}, {"id": "82SWVH2E"}, {"id": "JTYEPD92"}, {"id": "WAV7UIVR"}, {"id": "NM3SGS4X"}, {"id": "IBX4G3RQ"}, {"id": "WRCPUI4X"}, {"id": "PVGTI83X"}, {"id": "9ZFLXRC3"}, {"id": "L8IYN5ZP"}, {"id": "LCV9X2XP"}, {"id": "ADK3L4K5"}, {"id": "RB4Y9E6M"}, {"id": "UPZYZLJQ"}, {"id": "KHMGPHGF"}, {"id": "KP783F6E"}, {"id": "JCDCZUHK"}, {"id": "4AR6Z52H"}, {"id": "6NHHZCBM"}, {"id": "9NTFAVMI"}, {"id": "QESTKKUB"}, {"id": "RVGRUW8T"}, {"id": "K3BLD3K9"}, {"id": "K9RW7Y7W"}, {"id": "SJKPZKNF"}, {"id": "CKK2FTLH"}, {"id": "A59AGXF8"}, {"id": "YQDZ23QW"}, {"id": "4ZA3Y4DH"}, {"id": "EGLUJN9Y"}, {"id": "64BDP4KI"}], "links": [{"source": "2KXZIYTT", "target": "NHG4G4L4"}, {"source": "2KXZIYTT", "target": "32CEIHQE"}, {"source": "2KXZIYTT", "target": "J6X9FA8M"}, {"source": "2KXZIYTT", "target": "3ETZFFNS"}, {"source": "2KXZIYTT", "target": "FXISQ7ZW"}, {"source": "2KXZIYTT", "target": "9U7CKEUD"}, {"source": "2KXZIYTT", "target": "6BV8YS95"}, {"source": "2KXZIYTT", "target": "WAV7UIVR"}, {"source": "2KXZIYTT", "target": "33CHN65F"}, {"source": "EG5CF9XD", "target": "CDEE3MMB"}, {"source": "EG5CF9XD", "target": "KRL6I8BU"}, {"source": "EG5CF9XD", "target": "CH2I4QZD"}, {"source": "EG5CF9XD", "target": "HL2YSKU9"}, {"source": "EG5CF9XD", "target": "RTTHJN6V"}, {"source": "EG5CF9XD", "target": "6XE6BCA9"}, {"source": "EG5CF9XD", "target": "7LPQ6DBD"}, {"source": "EG5CF9XD", "target": "ASVT2FM6"}, {"source": "EG5CF9XD", "target": "37DD97CJ"}, {"source": "EG5CF9XD", "target": "7MYBEEJL"}, {"source": "EG5CF9XD", "target": "5G4IZVQ8"}, {"source": "EG5CF9XD", "target": "3SN7EBSL"}, {"source": "EG5CF9XD", "target": "CXAL64XJ"}, {"source": "EG5CF9XD", "target": "GVLDYG9U"}, {"source": "7CIQ9LTV", "target": "VK7MYWPG"}, {"source": "7CIQ9LTV", "target": "F9HV5EF8"}, {"source": "7CIQ9LTV", "target": "CH2I4QZD"}, {"source": "7CIQ9LTV", "target": "Z8I3GF4V"}, {"source": "7CIQ9LTV", "target": "VXZIU84M"}, {"source": "7CIQ9LTV", "target": "EAMLK3Y5"}, {"source": "7CIQ9LTV", "target": "PY7VZARY"}, {"source": "7CIQ9LTV", "target": "93EJ6DH8"}, {"source": "7CIQ9LTV", "target": "C4J4FFM6"}, {"source": "7CIQ9LTV", "target": "2CAC6487"}, {"source": "7CIQ9LTV", "target": "JQNL2KII"}, {"source": "7CIQ9LTV", "target": "26B4JXMQ"}, {"source": "7CIQ9LTV", "target": "RPTF5C6P"}, {"source": "7CIQ9LTV", "target": "EXENA72Y"}, {"source": "EAMLK3Y5", "target": "VK7MYWPG"}, {"source": "EAMLK3Y5", "target": "CH2I4QZD"}, {"source": "EAMLK3Y5", "target": "Z8I3GF4V"}, {"source": "EAMLK3Y5", "target": "C4J4FFM6"}, {"source": "EAMLK3Y5", "target": "DXJZBZW7"}, {"source": "EAMLK3Y5", "target": "GVLDYG9U"}, {"source": "EAMLK3Y5", "target": "LWR2AXGE"}, {"source": "JQNL2KII", "target": "VK7MYWPG"}, {"source": "JQNL2KII", "target": "I5GW9TLE"}, {"source": "JQNL2KII", "target": "MYBFDHFH"}, {"source": "JQNL2KII", "target": "LMIEMA55"}, {"source": "JQNL2KII", "target": "CH2I4QZD"}, {"source": "JQNL2KII", "target": "EAMLK3Y5"}, {"source": "JQNL2KII", "target": "Y2Y2RI89"}, {"source": "JQNL2KII", "target": "NA83BBQ9"}, {"source": "JQNL2KII", "target": "5NAEA23U"}, {"source": "JQNL2KII", "target": "2CGJFSN3"}, {"source": "JQNL2KII", "target": "93EJ6DH8"}, {"source": "JQNL2KII", "target": "C4J4FFM6"}, {"source": "JQNL2KII", "target": "EG5CF9XD"}, {"source": "JQNL2KII", "target": "BE48TX2H"}, {"source": "JQNL2KII", "target": "DVT2R32N"}, {"source": "JQNL2KII", "target": "NTUWGCDT"}, {"source": "JQNL2KII", "target": "3SN7EBSL"}, {"source": "JQNL2KII", "target": "TWSMZCW6"}, {"source": "JQNL2KII", "target": "E5UC3428"}, {"source": "JQNL2KII", "target": "UULVBDSB"}, {"source": "JQNL2KII", "target": "H9U8VET3"}, {"source": "JQNL2KII", "target": "NDBBXSFX"}, {"source": "JQNL2KII", "target": "NEY2LB77"}, {"source": "JQNL2KII", "target": "RJF67ZIL"}, {"source": "JQNL2KII", "target": "4LX92JX4"}, {"source": "JQNL2KII", "target": "F7ZF6LU6"}, {"source": "JQNL2KII", "target": "6E5KLX6X"}, {"source": "JQNL2KII", "target": "HS2MRUCX"}, {"source": "U68LQ887", "target": "VK7MYWPG"}, {"source": "U68LQ887", "target": "LN8M5Y5R"}, {"source": "U68LQ887", "target": "PY7VZARY"}, {"source": "U68LQ887", "target": "2CAC6487"}, {"source": "3SN7EBSL", "target": "ICIN6V7I"}, {"source": "3SN7EBSL", "target": "9TFDXLXF"}, {"source": "3SN7EBSL", "target": "CH2I4QZD"}, {"source": "3SN7EBSL", "target": "C2C72RPF"}, {"source": "3SN7EBSL", "target": "RTTHJN6V"}, {"source": "3SN7EBSL", "target": "5G4IZVQ8"}, {"source": "3SN7EBSL", "target": "TWSMZCW6"}, {"source": "3SN7EBSL", "target": "MFG9C974"}, {"source": "3SN7EBSL", "target": "DXJZBZW7"}, {"source": "3SN7EBSL", "target": "YH8A2UHK"}, {"source": "3SN7EBSL", "target": "MJUHEIIH"}, {"source": "3SN7EBSL", "target": "B6876BD4"}, {"source": "3SN7EBSL", "target": "RB4Y9E6M"}, {"source": "3ETZFFNS", "target": "GJ4QZKTS"}, {"source": "3ETZFFNS", "target": "KRL6I8BU"}, {"source": "3ETZFFNS", "target": "2XPA8DN6"}, {"source": "3ETZFFNS", "target": "6QHZ3LJG"}, {"source": "3ETZFFNS", "target": "ELI78EZX"}, {"source": "3ETZFFNS", "target": "RXLKGNDV"}, {"source": "3ETZFFNS", "target": "9Z7L9INV"}, {"source": "3ETZFFNS", "target": "RTTHJN6V"}, {"source": "3ETZFFNS", "target": "NB7I59CD"}, {"source": "3ETZFFNS", "target": "EG5CF9XD"}, {"source": "3ETZFFNS", "target": "WR44SNW8"}, {"source": "3ETZFFNS", "target": "34G9QI8T"}, {"source": "3ETZFFNS", "target": "7MYBEEJL"}, {"source": "3ETZFFNS", "target": "FXISQ7ZW"}, {"source": "3ETZFFNS", "target": "5G4IZVQ8"}, {"source": "3ETZFFNS", "target": "DNXZWQYC"}, {"source": "3ETZFFNS", "target": "TWSMZCW6"}, {"source": "3ETZFFNS", "target": "IDI6S8GS"}, {"source": "3ETZFFNS", "target": "YGRIWHW4"}, {"source": "3ETZFFNS", "target": "NEY2LB77"}, {"source": "3ETZFFNS", "target": "RJF67ZIL"}, {"source": "3ETZFFNS", "target": "CXAL64XJ"}, {"source": "3ETZFFNS", "target": "S9VWQ4SW"}, {"source": "3ETZFFNS", "target": "I95YCTJ8"}, {"source": "3ETZFFNS", "target": "4I95LEVG"}, {"source": "3ETZFFNS", "target": "H4D56SJW"}, {"source": "3ETZFFNS", "target": "XG33BSQ4"}, {"source": "3ETZFFNS", "target": "2FF2WT72"}, {"source": "3ETZFFNS", "target": "6BV8YS95"}, {"source": "3ETZFFNS", "target": "33CHN65F"}, {"source": "XSVIIP5L", "target": "GSRCBWKB"}, {"source": "XSVIIP5L", "target": "Q225KNMF"}, {"source": "XSVIIP5L", "target": "RMQ3FCG9"}, {"source": "XSVIIP5L", "target": "W7IDCXT4"}, {"source": "XSVIIP5L", "target": "HYTH7KQ5"}, {"source": "XSVIIP5L", "target": "B6CEU5DC"}, {"source": "XSVIIP5L", "target": "DSQIERIF"}, {"source": "XSVIIP5L", "target": "ZYA68N2R"}, {"source": "XSVIIP5L", "target": "TC9VUUIV"}, {"source": "XSVIIP5L", "target": "PY7VZARY"}, {"source": "XSVIIP5L", "target": "C4J4FFM6"}, {"source": "XSVIIP5L", "target": "2CAC6487"}, {"source": "XSVIIP5L", "target": "6SUNA9ZC"}, {"source": "XSVIIP5L", "target": "VR4FDYCU"}, {"source": "XSVIIP5L", "target": "ZVE482RF"}, {"source": "XSVIIP5L", "target": "YLP38A4R"}, {"source": "XSVIIP5L", "target": "3N9XWYFJ"}, {"source": "XSVIIP5L", "target": "GJHWZHKJ"}, {"source": "XSVIIP5L", "target": "Q7HDXF92"}, {"source": "XSVIIP5L", "target": "M8IEXC3J"}, {"source": "XSVIIP5L", "target": "U68LQ887"}, {"source": "ZBR2P2MG", "target": "GSRCBWKB"}, {"source": "ZBR2P2MG", "target": "Q225KNMF"}, {"source": "ZBR2P2MG", "target": "9H25VNYG"}, {"source": "ZBR2P2MG", "target": "WKK56EXU"}, {"source": "ZBR2P2MG", "target": "RTTHJN6V"}, {"source": "ZBR2P2MG", "target": "TC9VUUIV"}, {"source": "ZBR2P2MG", "target": "PY7VZARY"}, {"source": "ZBR2P2MG", "target": "2CGJFSN3"}, {"source": "ZBR2P2MG", "target": "C4J4FFM6"}, {"source": "ZBR2P2MG", "target": "2CAC6487"}, {"source": "ZBR2P2MG", "target": "JQNL2KII"}, {"source": "ZBR2P2MG", "target": "3IKXM4X7"}, {"source": "ZBR2P2MG", "target": "IIM9QZV9"}, {"source": "ZBR2P2MG", "target": "F9VLX7PS"}, {"source": "ZBR2P2MG", "target": "7MYBEEJL"}, {"source": "ZBR2P2MG", "target": "5G4IZVQ8"}, {"source": "ZBR2P2MG", "target": "DNXZWQYC"}, {"source": "ZBR2P2MG", "target": "636EBTU9"}, {"source": "ZBR2P2MG", "target": "ZTIJEPMW"}, {"source": "ZBR2P2MG", "target": "SHZBLVNX"}, {"source": "ZBR2P2MG", "target": "RPTF5C6P"}, {"source": "ZBR2P2MG", "target": "3K2FESNS"}, {"source": "83CAPN4G", "target": "NEBJ85H3"}, {"source": "83CAPN4G", "target": "LN8M5Y5R"}, {"source": "83CAPN4G", "target": "DDERN2U3"}, {"source": "83CAPN4G", "target": "FM9IYRTX"}, {"source": "83CAPN4G", "target": "UMVINAGY"}, {"source": "83CAPN4G", "target": "LG3FSWHQ"}, {"source": "83CAPN4G", "target": "TCSF3QRJ"}, {"source": "83CAPN4G", "target": "IBSKB9AS"}, {"source": "83CAPN4G", "target": "ZRBMFYZM"}, {"source": "83CAPN4G", "target": "HYTH7KQ5"}, {"source": "83CAPN4G", "target": "235TMJP4"}, {"source": "83CAPN4G", "target": "C2C72RPF"}, {"source": "83CAPN4G", "target": "AKJLN7GG"}, {"source": "83CAPN4G", "target": "2I4CNINN"}, {"source": "83CAPN4G", "target": "GJK38T9U"}, {"source": "83CAPN4G", "target": "4DHQNXK9"}, {"source": "83CAPN4G", "target": "3ETZFFNS"}, {"source": "83CAPN4G", "target": "YGRIWHW4"}, {"source": "83CAPN4G", "target": "636EBTU9"}, {"source": "83CAPN4G", "target": "FE8FP9D7"}, {"source": "83CAPN4G", "target": "SBR8JG4H"}, {"source": "83CAPN4G", "target": "AD25IKQR"}, {"source": "83CAPN4G", "target": "V4RID8TN"}, {"source": "83CAPN4G", "target": "3N9XWYFJ"}, {"source": "83CAPN4G", "target": "SFKG795G"}, {"source": "83CAPN4G", "target": "4VVW4E7R"}, {"source": "83CAPN4G", "target": "6PCTX6BW"}, {"source": "83CAPN4G", "target": "YELA7MTZ"}, {"source": "83CAPN4G", "target": "5JHNYD2W"}, {"source": "83CAPN4G", "target": "SHZBLVNX"}, {"source": "83CAPN4G", "target": "7QGFCBNH"}, {"source": "RS5DBPDD", "target": "NEBJ85H3"}, {"source": "RS5DBPDD", "target": "7SQSUAJJ"}, {"source": "RS5DBPDD", "target": "JW4WDRBE"}, {"source": "RS5DBPDD", "target": "MYJM3I6X"}, {"source": "RS5DBPDD", "target": "RTTHJN6V"}, {"source": "RS5DBPDD", "target": "NB7I59CD"}, {"source": "RS5DBPDD", "target": "2CGJFSN3"}, {"source": "RS5DBPDD", "target": "C4J4FFM6"}, {"source": "RS5DBPDD", "target": "I8XV7B38"}, {"source": "RS5DBPDD", "target": "XB78ZGFK"}, {"source": "RS5DBPDD", "target": "34G9QI8T"}, {"source": "RS5DBPDD", "target": "7MYBEEJL"}, {"source": "RS5DBPDD", "target": "5G4IZVQ8"}, {"source": "RS5DBPDD", "target": "YLP38A4R"}, {"source": "RS5DBPDD", "target": "3N9XWYFJ"}, {"source": "RS5DBPDD", "target": "YGSP98R9"}, {"source": "RS5DBPDD", "target": "4VVW4E7R"}, {"source": "RS5DBPDD", "target": "WVU5AFQJ"}, {"source": "RS5DBPDD", "target": "Z4KN26RY"}, {"source": "RS5DBPDD", "target": "LBRII9F5"}, {"source": "RS5DBPDD", "target": "M8IEXC3J"}, {"source": "RS5DBPDD", "target": "SHZBLVNX"}, {"source": "RS5DBPDD", "target": "ZBR2P2MG"}, {"source": "RS5DBPDD", "target": "7QGFCBNH"}, {"source": "7QGFCBNH", "target": "NN8RWTJN"}, {"source": "7QGFCBNH", "target": "NV5PBDVV"}, {"source": "7QGFCBNH", "target": "2CGJFSN3"}, {"source": "7QGFCBNH", "target": "DNXZWQYC"}, {"source": "7QGFCBNH", "target": "2KXZIYTT"}, {"source": "7QGFCBNH", "target": "SHZBLVNX"}, {"source": "7QGFCBNH", "target": "ZBR2P2MG"}, {"source": "7QGFCBNH", "target": "RPTF5C6P"}, {"source": "7QGFCBNH", "target": "CEDN8EB5"}, {"source": "7QGFCBNH", "target": "3K2FESNS"}, {"source": "7QGFCBNH", "target": "GPPFNCKA"}, {"source": "AN4VBEKF", "target": "NN8RWTJN"}, {"source": "AN4VBEKF", "target": "LN8M5Y5R"}, {"source": "AN4VBEKF", "target": "XRBM2DC8"}, {"source": "AN4VBEKF", "target": "G73KS8UQ"}, {"source": "AN4VBEKF", "target": "YETHSI88"}, {"source": "AN4VBEKF", "target": "7SQSUAJJ"}, {"source": "AN4VBEKF", "target": "B84VKLW9"}, {"source": "AN4VBEKF", "target": "GJK38T9U"}, {"source": "AN4VBEKF", "target": "ULBJ2U9F"}, {"source": "AN4VBEKF", "target": "3ETZFFNS"}, {"source": "AN4VBEKF", "target": "FXISQ7ZW"}, {"source": "AN4VBEKF", "target": "AD25IKQR"}, {"source": "AN4VBEKF", "target": "V4RID8TN"}, {"source": "AN4VBEKF", "target": "RS5DBPDD"}, {"source": "AN4VBEKF", "target": "YGSP98R9"}, {"source": "AN4VBEKF", "target": "4VVW4E7R"}, {"source": "AN4VBEKF", "target": "WVU5AFQJ"}, {"source": "AN4VBEKF", "target": "Z4KN26RY"}, {"source": "AN4VBEKF", "target": "2KXZIYTT"}, {"source": "AN4VBEKF", "target": "7QGFCBNH"}, {"source": "EJENTABB", "target": "NN8RWTJN"}, {"source": "EJENTABB", "target": "LN8M5Y5R"}, {"source": "EJENTABB", "target": "XRBM2DC8"}, {"source": "EJENTABB", "target": "2WFBYTCC"}, {"source": "EJENTABB", "target": "G73KS8UQ"}, {"source": "EJENTABB", "target": "YETHSI88"}, {"source": "EJENTABB", "target": "7SQSUAJJ"}, {"source": "EJENTABB", "target": "B84VKLW9"}, {"source": "EJENTABB", "target": "GJK38T9U"}, {"source": "EJENTABB", "target": "HFV4ZKWJ"}, {"source": "EJENTABB", "target": "ULBJ2U9F"}, {"source": "EJENTABB", "target": "3ETZFFNS"}, {"source": "EJENTABB", "target": "FXISQ7ZW"}, {"source": "EJENTABB", "target": "8HFVN58A"}, {"source": "EJENTABB", "target": "AD25IKQR"}, {"source": "EJENTABB", "target": "RS5DBPDD"}, {"source": "EJENTABB", "target": "U2ZWMF5Q"}, {"source": "EJENTABB", "target": "YGSP98R9"}, {"source": "EJENTABB", "target": "4VVW4E7R"}, {"source": "EJENTABB", "target": "IPC36S5V"}, {"source": "EJENTABB", "target": "DN3YBFQM"}, {"source": "EJENTABB", "target": "WVU5AFQJ"}, {"source": "EJENTABB", "target": "Z4KN26RY"}, {"source": "EJENTABB", "target": "2KXZIYTT"}, {"source": "EJENTABB", "target": "7QGFCBNH"}, {"source": "7WSWWYHM", "target": "KRL6I8BU"}, {"source": "7WSWWYHM", "target": "6H2ECTR5"}, {"source": "7WSWWYHM", "target": "FEA27PZK"}, {"source": "7WSWWYHM", "target": "TC9VUUIV"}, {"source": "7WSWWYHM", "target": "C4J4FFM6"}, {"source": "7WSWWYHM", "target": "2CAC6487"}, {"source": "7WSWWYHM", "target": "3ETZFFNS"}, {"source": "7WSWWYHM", "target": "LXMLAZEY"}, {"source": "7WSWWYHM", "target": "GTTJ59J6"}, {"source": "7WSWWYHM", "target": "CNHW6H66"}, {"source": "7WSWWYHM", "target": "PJN6ACVA"}, {"source": "7WSWWYHM", "target": "8J6EQLST"}, {"source": "7WSWWYHM", "target": "4VVW4E7R"}, {"source": "7WSWWYHM", "target": "4I95LEVG"}, {"source": "7WSWWYHM", "target": "ZBR2P2MG"}, {"source": "7WSWWYHM", "target": "7QGFCBNH"}, {"source": "A6HRG4JG", "target": "KRL6I8BU"}, {"source": "A6HRG4JG", "target": "DDERN2U3"}, {"source": "A6HRG4JG", "target": "P72B2DSD"}, {"source": "A6HRG4JG", "target": "E4ZYMDJZ"}, {"source": "A6HRG4JG", "target": "NMVTYI5T"}, {"source": "A6HRG4JG", "target": "2MJK8MHP"}, {"source": "A6HRG4JG", "target": "DSQIERIF"}, {"source": "A6HRG4JG", "target": "AKJLN7GG"}, {"source": "A6HRG4JG", "target": "FTIE73TX"}, {"source": "A6HRG4JG", "target": "QGBJAIEI"}, {"source": "A6HRG4JG", "target": "9ADQIL25"}, {"source": "A6HRG4JG", "target": "ILEWWFTT"}, {"source": "A6HRG4JG", "target": "EHMGQ9UD"}, {"source": "A6HRG4JG", "target": "JF88W22K"}, {"source": "A6HRG4JG", "target": "GU755I44"}, {"source": "A6HRG4JG", "target": "KV8PHWTV"}, {"source": "A6HRG4JG", "target": "ULBJ2U9F"}, {"source": "A6HRG4JG", "target": "W3N99HTI"}, {"source": "A6HRG4JG", "target": "WPVJ7BMX"}, {"source": "A6HRG4JG", "target": "3CK55IK5"}, {"source": "A6HRG4JG", "target": "RTTHJN6V"}, {"source": "A6HRG4JG", "target": "I9WRBFTN"}, {"source": "A6HRG4JG", "target": "EJDM67E3"}, {"source": "A6HRG4JG", "target": "3ETZFFNS"}, {"source": "A6HRG4JG", "target": "XH9L2QDC"}, {"source": "A6HRG4JG", "target": "XB78ZGFK"}, {"source": "A6HRG4JG", "target": "AHUR6D8V"}, {"source": "A6HRG4JG", "target": "ADBR8XLT"}, {"source": "A6HRG4JG", "target": "7QKHXR48"}, {"source": "A6HRG4JG", "target": "F2L78HEX"}, {"source": "A6HRG4JG", "target": "L8NXQD2H"}, {"source": "A6HRG4JG", "target": "6SUNA9ZC"}, {"source": "A6HRG4JG", "target": "AIHUXYD5"}, {"source": "A6HRG4JG", "target": "MAXAKMU3"}, {"source": "A6HRG4JG", "target": "VR4FDYCU"}, {"source": "A6HRG4JG", "target": "LXMLAZEY"}, {"source": "A6HRG4JG", "target": "DXXKQ7T9"}, {"source": "A6HRG4JG", "target": "8HFVN58A"}, {"source": "A6HRG4JG", "target": "5Z3LQNLZ"}, {"source": "A6HRG4JG", "target": "VQNTBV95"}, {"source": "A6HRG4JG", "target": "L8NRCZ8E"}, {"source": "A6HRG4JG", "target": "C6YPQLJI"}, {"source": "A6HRG4JG", "target": "ICGJ5R6J"}, {"source": "A6HRG4JG", "target": "AD25IKQR"}, {"source": "A6HRG4JG", "target": "YLP38A4R"}, {"source": "A6HRG4JG", "target": "V4RID8TN"}, {"source": "A6HRG4JG", "target": "3N9XWYFJ"}, {"source": "A6HRG4JG", "target": "83CAPN4G"}, {"source": "A6HRG4JG", "target": "RS5DBPDD"}, {"source": "A6HRG4JG", "target": "EJENTABB"}, {"source": "A6HRG4JG", "target": "AN4VBEKF"}, {"source": "A6HRG4JG", "target": "AR2BHG9K"}, {"source": "A6HRG4JG", "target": "LJZB6MTP"}, {"source": "A6HRG4JG", "target": "XSVIIP5L"}, {"source": "A6HRG4JG", "target": "FQTXYHMF"}, {"source": "A6HRG4JG", "target": "GJHWZHKJ"}, {"source": "A6HRG4JG", "target": "MRQB7B6N"}, {"source": "A6HRG4JG", "target": "U2ZWMF5Q"}, {"source": "A6HRG4JG", "target": "4VVW4E7R"}, {"source": "A6HRG4JG", "target": "Q7HDXF92"}, {"source": "A6HRG4JG", "target": "IPC36S5V"}, {"source": "A6HRG4JG", "target": "WVU5AFQJ"}, {"source": "A6HRG4JG", "target": "ELW3I7GH"}, {"source": "A6HRG4JG", "target": "Z4KN26RY"}, {"source": "A6HRG4JG", "target": "6PCTX6BW"}, {"source": "A6HRG4JG", "target": "YQWKSHX5"}, {"source": "A6HRG4JG", "target": "LBRII9F5"}, {"source": "A6HRG4JG", "target": "M8IEXC3J"}, {"source": "A6HRG4JG", "target": "TJM5C3QJ"}, {"source": "A6HRG4JG", "target": "SHZBLVNX"}, {"source": "A6HRG4JG", "target": "ZBR2P2MG"}, {"source": "A6HRG4JG", "target": "7QGFCBNH"}, {"source": "3N9XWYFJ", "target": "5E5QUP9L"}, {"source": "3N9XWYFJ", "target": "TD9CJZTL"}, {"source": "3N9XWYFJ", "target": "G73KS8UQ"}, {"source": "3N9XWYFJ", "target": "HYTH7KQ5"}, {"source": "3N9XWYFJ", "target": "DFHWY9KT"}, {"source": "3N9XWYFJ", "target": "TC9VUUIV"}, {"source": "3N9XWYFJ", "target": "5NAEA23U"}, {"source": "3N9XWYFJ", "target": "C4J4FFM6"}, {"source": "3N9XWYFJ", "target": "WR44SNW8"}, {"source": "3N9XWYFJ", "target": "3ETZFFNS"}, {"source": "3N9XWYFJ", "target": "34G9QI8T"}, {"source": "3N9XWYFJ", "target": "THS8SVYY"}, {"source": "3N9XWYFJ", "target": "E5UC3428"}, {"source": "3N9XWYFJ", "target": "636EBTU9"}, {"source": "3N9XWYFJ", "target": "YS4B79SA"}, {"source": "3N9XWYFJ", "target": "7GJ3IZ6V"}, {"source": "3N9XWYFJ", "target": "ZTIJEPMW"}, {"source": "3N9XWYFJ", "target": "DXXKQ7T9"}, {"source": "3N9XWYFJ", "target": "7WSWWYHM"}, {"source": "3N9XWYFJ", "target": "AD25IKQR"}, {"source": "3N9XWYFJ", "target": "YLP38A4R"}, {"source": "3N9XWYFJ", "target": "HLGK973Q"}, {"source": "3N9XWYFJ", "target": "V4RID8TN"}, {"source": "3N9XWYFJ", "target": "YGSP98R9"}, {"source": "3N9XWYFJ", "target": "4VVW4E7R"}, {"source": "3N9XWYFJ", "target": "6PCTX6BW"}, {"source": "3N9XWYFJ", "target": "LBRII9F5"}, {"source": "3N9XWYFJ", "target": "YELA7MTZ"}, {"source": "3N9XWYFJ", "target": "M8IEXC3J"}, {"source": "3N9XWYFJ", "target": "IBX4G3RQ"}, {"source": "3N9XWYFJ", "target": "ZBR2P2MG"}, {"source": "3N9XWYFJ", "target": "7QGFCBNH"}, {"source": "VFE2E59A", "target": "5E5QUP9L"}, {"source": "VFE2E59A", "target": "YE8B4L3K"}, {"source": "VFE2E59A", "target": "TD9CJZTL"}, {"source": "VFE2E59A", "target": "LCJ7JX6X"}, {"source": "VFE2E59A", "target": "2I4CNINN"}, {"source": "VFE2E59A", "target": "5XDSJYDQ"}, {"source": "VFE2E59A", "target": "B7LHX58X"}, {"source": "VFE2E59A", "target": "XLH4GHSA"}, {"source": "VFE2E59A", "target": "GJK38T9U"}, {"source": "VFE2E59A", "target": "HA9SMVE4"}, {"source": "VFE2E59A", "target": "C4J4FFM6"}, {"source": "VFE2E59A", "target": "3FP23RSV"}, {"source": "VFE2E59A", "target": "PJN6ACVA"}, {"source": "VFE2E59A", "target": "YLP38A4R"}, {"source": "VFE2E59A", "target": "HLGK973Q"}, {"source": "VFE2E59A", "target": "VFE2E59A"}, {"source": "VFE2E59A", "target": "TR6PDBUB"}, {"source": "VFE2E59A", "target": "M8IEXC3J"}, {"source": "VFE2E59A", "target": "PN4KZW88"}, {"source": "VFE2E59A", "target": "LG56XJV4"}, {"source": "VFE2E59A", "target": "5XYEWJ56"}, {"source": "VFE2E59A", "target": "4YVM9SWB"}, {"source": "VFE2E59A", "target": "KHMGPHGF"}, {"source": "YLP38A4R", "target": "5E5QUP9L"}, {"source": "YLP38A4R", "target": "6H2ECTR5"}, {"source": "YLP38A4R", "target": "9ELBEP7C"}, {"source": "YLP38A4R", "target": "WKK56EXU"}, {"source": "YLP38A4R", "target": "HA9SMVE4"}, {"source": "YLP38A4R", "target": "7WSWWYHM"}, {"source": "YLP38A4R", "target": "4VVW4E7R"}, {"source": "YLP38A4R", "target": "LBRII9F5"}, {"source": "YLP38A4R", "target": "7QGFCBNH"}, {"source": "DN3YBFQM", "target": "DDERN2U3"}, {"source": "DN3YBFQM", "target": "3K8QPXKB"}, {"source": "DN3YBFQM", "target": "DPYVT2TP"}, {"source": "DN3YBFQM", "target": "PJN6ACVA"}, {"source": "DN3YBFQM", "target": "HLGK973Q"}, {"source": "DN3YBFQM", "target": "67IANJIE"}, {"source": "DN3YBFQM", "target": "VFE2E59A"}, {"source": "DN3YBFQM", "target": "TR6PDBUB"}, {"source": "DN3YBFQM", "target": "LS3DVSRL"}, {"source": "DN3YBFQM", "target": "PN4KZW88"}, {"source": "DN3YBFQM", "target": "84BTZRXE"}, {"source": "DN3YBFQM", "target": "YVNDG5GA"}, {"source": "DN3YBFQM", "target": "GPTDRNJR"}, {"source": "DN3YBFQM", "target": "F89Z26U4"}, {"source": "DN3YBFQM", "target": "4SHNAL4U"}, {"source": "DN3YBFQM", "target": "JCDCZUHK"}, {"source": "DN3YBFQM", "target": "6NHHZCBM"}, {"source": "TR6PDBUB", "target": "DDERN2U3"}, {"source": "TR6PDBUB", "target": "2CAC6487"}, {"source": "TR6PDBUB", "target": "JQNL2KII"}, {"source": "TR6PDBUB", "target": "BE48TX2H"}, {"source": "TR6PDBUB", "target": "NTUWGCDT"}, {"source": "TR6PDBUB", "target": "3SN7EBSL"}, {"source": "TR6PDBUB", "target": "7GJ3IZ6V"}, {"source": "TR6PDBUB", "target": "GVLDYG9U"}, {"source": "TR6PDBUB", "target": "B6876BD4"}, {"source": "TR6PDBUB", "target": "YLP38A4R"}, {"source": "TR6PDBUB", "target": "HLGK973Q"}, {"source": "TR6PDBUB", "target": "4VVW4E7R"}, {"source": "TR6PDBUB", "target": "6PCTX6BW"}, {"source": "TR6PDBUB", "target": "LBRII9F5"}, {"source": "TR6PDBUB", "target": "PN4KZW88"}, {"source": "TR6PDBUB", "target": "GPTDRNJR"}, {"source": "TR6PDBUB", "target": "ZBR2P2MG"}, {"source": "TR6PDBUB", "target": "ADK3L4K5"}, {"source": "TR6PDBUB", "target": "7QGFCBNH"}, {"source": "TR6PDBUB", "target": "Q473REEE"}, {"source": "TR6PDBUB", "target": "KP783F6E"}, {"source": "V4RID8TN", "target": "DDERN2U3"}, {"source": "V4RID8TN", "target": "HYTH7KQ5"}, {"source": "V4RID8TN", "target": "GJK38T9U"}, {"source": "V4RID8TN", "target": "DFHWY9KT"}, {"source": "V4RID8TN", "target": "W6FQ3KJ5"}, {"source": "V4RID8TN", "target": "CWKWIWG4"}, {"source": "V4RID8TN", "target": "I9WRBFTN"}, {"source": "V4RID8TN", "target": "2CGJFSN3"}, {"source": "V4RID8TN", "target": "6XE6BCA9"}, {"source": "V4RID8TN", "target": "3ETZFFNS"}, {"source": "V4RID8TN", "target": "JQNL2KII"}, {"source": "V4RID8TN", "target": "NZ9HRJ7K"}, {"source": "V4RID8TN", "target": "FXISQ7ZW"}, {"source": "V4RID8TN", "target": "Y5JVH5WE"}, {"source": "V4RID8TN", "target": "7WSWWYHM"}, {"source": "V4RID8TN", "target": "YLP38A4R"}, {"source": "V4RID8TN", "target": "HLGK973Q"}, {"source": "V4RID8TN", "target": "V4RID8TN"}, {"source": "V4RID8TN", "target": "YGSP98R9"}, {"source": "V4RID8TN", "target": "4VVW4E7R"}, {"source": "V4RID8TN", "target": "6PCTX6BW"}, {"source": "V4RID8TN", "target": "LBRII9F5"}, {"source": "V4RID8TN", "target": "YELA7MTZ"}, {"source": "V4RID8TN", "target": "M8IEXC3J"}, {"source": "V4RID8TN", "target": "2KXZIYTT"}, {"source": "V4RID8TN", "target": "S9VWQ4SW"}, {"source": "V4RID8TN", "target": "5JHNYD2W"}, {"source": "V4RID8TN", "target": "RV42EVAU"}, {"source": "V4RID8TN", "target": "SHZBLVNX"}, {"source": "V4RID8TN", "target": "ZBR2P2MG"}, {"source": "V4RID8TN", "target": "Z52SMZ9I"}, {"source": "V4RID8TN", "target": "CEDN8EB5"}, {"source": "V4RID8TN", "target": "7QGFCBNH"}, {"source": "V4RID8TN", "target": "33CHN65F"}, {"source": "YGSP98R9", "target": "DDERN2U3"}, {"source": "YGSP98R9", "target": "2CAC6487"}, {"source": "YGSP98R9", "target": "JQNL2KII"}, {"source": "YGSP98R9", "target": "GVLDYG9U"}, {"source": "YGSP98R9", "target": "HLGK973Q"}, {"source": "YGSP98R9", "target": "4VVW4E7R"}, {"source": "YGSP98R9", "target": "6PCTX6BW"}, {"source": "YGSP98R9", "target": "LBRII9F5"}, {"source": "YGSP98R9", "target": "PN4KZW88"}, {"source": "YGSP98R9", "target": "ZBR2P2MG"}, {"source": "YGSP98R9", "target": "RPTF5C6P"}, {"source": "YGSP98R9", "target": "ADK3L4K5"}, {"source": "YGSP98R9", "target": "7QGFCBNH"}, {"source": "YGSP98R9", "target": "EXENA72Y"}, {"source": "4VVW4E7R", "target": "6H2ECTR5"}, {"source": "4VVW4E7R", "target": "UMVINAGY"}, {"source": "4VVW4E7R", "target": "PY7VZARY"}, {"source": "4VVW4E7R", "target": "2KXZIYTT"}, {"source": "4VVW4E7R", "target": "SHZBLVNX"}, {"source": "4VVW4E7R", "target": "ZBR2P2MG"}, {"source": "4VVW4E7R", "target": "7QGFCBNH"}, {"source": "LJZB6MTP", "target": "6H2ECTR5"}, {"source": "LJZB6MTP", "target": "9ELBEP7C"}, {"source": "LJZB6MTP", "target": "S68H9QBG"}, {"source": "LJZB6MTP", "target": "Q3LGUB6S"}, {"source": "LJZB6MTP", "target": "MYJM3I6X"}, {"source": "LJZB6MTP", "target": "YLP38A4R"}, {"source": "LJZB6MTP", "target": "V4RID8TN"}, {"source": "LJZB6MTP", "target": "PR2LV2XL"}, {"source": "LJZB6MTP", "target": "RS5DBPDD"}, {"source": "LJZB6MTP", "target": "AN4VBEKF"}, {"source": "LJZB6MTP", "target": "4VVW4E7R"}, {"source": "LJZB6MTP", "target": "M8IEXC3J"}, {"source": "LJZB6MTP", "target": "ZBR2P2MG"}, {"source": "LJZB6MTP", "target": "7QGFCBNH"}, {"source": "DXGRXYA2", "target": "ZPB288VA"}, {"source": "DXGRXYA2", "target": "MYJM3I6X"}, {"source": "DXGRXYA2", "target": "7MYBEEJL"}, {"source": "DXGRXYA2", "target": "F2L78HEX"}, {"source": "DXGRXYA2", "target": "VR4FDYCU"}, {"source": "DXGRXYA2", "target": "7WSWWYHM"}, {"source": "DXGRXYA2", "target": "3N9XWYFJ"}, {"source": "DXGRXYA2", "target": "RS5DBPDD"}, {"source": "DXGRXYA2", "target": "AR2BHG9K"}, {"source": "DXGRXYA2", "target": "LJZB6MTP"}, {"source": "DXGRXYA2", "target": "FQTXYHMF"}, {"source": "DXGRXYA2", "target": "C44N7NAR"}, {"source": "DXGRXYA2", "target": "I55QRACV"}, {"source": "DXGRXYA2", "target": "A6HRG4JG"}, {"source": "DXGRXYA2", "target": "MRQB7B6N"}, {"source": "DXGRXYA2", "target": "Q7HDXF92"}, {"source": "DXGRXYA2", "target": "EXE29BH4"}, {"source": "DXGRXYA2", "target": "WVU5AFQJ"}, {"source": "DXGRXYA2", "target": "J7JUTEAB"}, {"source": "DXGRXYA2", "target": "7QGFCBNH"}, {"source": "FQTXYHMF", "target": "RMQ3FCG9"}, {"source": "FQTXYHMF", "target": "2MJK8MHP"}, {"source": "FQTXYHMF", "target": "DSQIERIF"}, {"source": "FQTXYHMF", "target": "B84VKLW9"}, {"source": "FQTXYHMF", "target": "KKPRRYF5"}, {"source": "FQTXYHMF", "target": "RTTHJN6V"}, {"source": "FQTXYHMF", "target": "TC9VUUIV"}, {"source": "FQTXYHMF", "target": "I9WRBFTN"}, {"source": "FQTXYHMF", "target": "2CGJFSN3"}, {"source": "FQTXYHMF", "target": "C4J4FFM6"}, {"source": "FQTXYHMF", "target": "2CAC6487"}, {"source": "FQTXYHMF", "target": "3ETZFFNS"}, {"source": "FQTXYHMF", "target": "AGD66LJC"}, {"source": "FQTXYHMF", "target": "564YS9JY"}, {"source": "FQTXYHMF", "target": "JQNL2KII"}, {"source": "FQTXYHMF", "target": "5G4IZVQ8"}, {"source": "FQTXYHMF", "target": "TWSMZCW6"}, {"source": "FQTXYHMF", "target": "F2L78HEX"}, {"source": "FQTXYHMF", "target": "6SUNA9ZC"}, {"source": "FQTXYHMF", "target": "AIHUXYD5"}, {"source": "FQTXYHMF", "target": "VR4FDYCU"}, {"source": "FQTXYHMF", "target": "636EBTU9"}, {"source": "FQTXYHMF", "target": "FE8FP9D7"}, {"source": "FQTXYHMF", "target": "DXXKQ7T9"}, {"source": "FQTXYHMF", "target": "GVLDYG9U"}, {"source": "FQTXYHMF", "target": "AD25IKQR"}, {"source": "FQTXYHMF", "target": "YLP38A4R"}, {"source": "FQTXYHMF", "target": "3N9XWYFJ"}, {"source": "FQTXYHMF", "target": "PR2LV2XL"}, {"source": "FQTXYHMF", "target": "RS5DBPDD"}, {"source": "FQTXYHMF", "target": "AN4VBEKF"}, {"source": "FQTXYHMF", "target": "AR2BHG9K"}, {"source": "FQTXYHMF", "target": "LJZB6MTP"}, {"source": "FQTXYHMF", "target": "XSVIIP5L"}, {"source": "FQTXYHMF", "target": "GJHWZHKJ"}, {"source": "FQTXYHMF", "target": "U2ZWMF5Q"}, {"source": "FQTXYHMF", "target": "YGSP98R9"}, {"source": "FQTXYHMF", "target": "Q7HDXF92"}, {"source": "FQTXYHMF", "target": "EXE29BH4"}, {"source": "FQTXYHMF", "target": "QU7MV362"}, {"source": "FQTXYHMF", "target": "WVU5AFQJ"}, {"source": "FQTXYHMF", "target": "ELW3I7GH"}, {"source": "FQTXYHMF", "target": "6PCTX6BW"}, {"source": "FQTXYHMF", "target": "EFJYEVC6"}, {"source": "FQTXYHMF", "target": "YQWKSHX5"}, {"source": "FQTXYHMF", "target": "LBRII9F5"}, {"source": "FQTXYHMF", "target": "J7JUTEAB"}, {"source": "FQTXYHMF", "target": "9D6RLLGK"}, {"source": "FQTXYHMF", "target": "IK5VV9S6"}, {"source": "FQTXYHMF", "target": "SHZBLVNX"}, {"source": "FQTXYHMF", "target": "ZBR2P2MG"}, {"source": "FQTXYHMF", "target": "7QGFCBNH"}, {"source": "AD25IKQR", "target": "UMVINAGY"}, {"source": "AD25IKQR", "target": "692FHSHH"}, {"source": "AD25IKQR", "target": "NB7I59CD"}, {"source": "AD25IKQR", "target": "EJDM67E3"}, {"source": "AD25IKQR", "target": "WR44SNW8"}, {"source": "AD25IKQR", "target": "3ETZFFNS"}, {"source": "AD25IKQR", "target": "N9CJVIAZ"}, {"source": "AD25IKQR", "target": "XB78ZGFK"}, {"source": "AD25IKQR", "target": "34G9QI8T"}, {"source": "AD25IKQR", "target": "DNXZWQYC"}, {"source": "AD25IKQR", "target": "EI2PAMBG"}, {"source": "AD25IKQR", "target": "7GJ3IZ6V"}, {"source": "AD25IKQR", "target": "4VVW4E7R"}, {"source": "AD25IKQR", "target": "9ZFLXRC3"}, {"source": "AD25IKQR", "target": "ZBR2P2MG"}, {"source": "AD25IKQR", "target": "7QGFCBNH"}, {"source": "DNXZWQYC", "target": "UMVINAGY"}, {"source": "DNXZWQYC", "target": "9TFDXLXF"}, {"source": "DNXZWQYC", "target": "6QHZ3LJG"}, {"source": "DNXZWQYC", "target": "TIPI8I2W"}, {"source": "DNXZWQYC", "target": "V8SPNVP5"}, {"source": "DNXZWQYC", "target": "C2C72RPF"}, {"source": "DNXZWQYC", "target": "7MYBEEJL"}, {"source": "DNXZWQYC", "target": "FXISQ7ZW"}, {"source": "DNXZWQYC", "target": "5G4IZVQ8"}, {"source": "DNXZWQYC", "target": "TWSMZCW6"}, {"source": "DNXZWQYC", "target": "REGGRY8M"}, {"source": "DNXZWQYC", "target": "B7FRA7CR"}, {"source": "DNXZWQYC", "target": "8FV8H8WB"}, {"source": "DNXZWQYC", "target": "8EZM6ZYV"}, {"source": "DNXZWQYC", "target": "33CHN65F"}, {"source": "WR44SNW8", "target": "UMVINAGY"}, {"source": "WR44SNW8", "target": "6QHZ3LJG"}, {"source": "WR44SNW8", "target": "7MYBEEJL"}, {"source": "WR44SNW8", "target": "5G4IZVQ8"}, {"source": "WR44SNW8", "target": "DNXZWQYC"}, {"source": "WR44SNW8", "target": "TWSMZCW6"}, {"source": "WR44SNW8", "target": "H9U8VET3"}, {"source": "WR44SNW8", "target": "RJF67ZIL"}, {"source": "WR44SNW8", "target": "QIAUJG5Q"}, {"source": "WR44SNW8", "target": "N8IBRSYQ"}, {"source": "WR44SNW8", "target": "GVLDYG9U"}, {"source": "WR44SNW8", "target": "IBX4G3RQ"}, {"source": "5UEP6FJF", "target": "2WFBYTCC"}, {"source": "5UEP6FJF", "target": "UW3MAL32"}, {"source": "5UEP6FJF", "target": "34G9QI8T"}, {"source": "5UEP6FJF", "target": "5G4IZVQ8"}, {"source": "5UEP6FJF", "target": "Y4DL944F"}, {"source": "5UEP6FJF", "target": "74K4782Q"}, {"source": "MRQB7B6N", "target": "9ELBEP7C"}, {"source": "MRQB7B6N", "target": "6Q6LWBNP"}, {"source": "MRQB7B6N", "target": "EJENTABB"}, {"source": "MRQB7B6N", "target": "AN4VBEKF"}, {"source": "MRQB7B6N", "target": "LJZB6MTP"}, {"source": "MRQB7B6N", "target": "ELW3I7GH"}, {"source": "MRQB7B6N", "target": "YQWKSHX5"}, {"source": "GPPFNCKA", "target": "QCGLBTNH"}, {"source": "GPPFNCKA", "target": "5NAEA23U"}, {"source": "GPPFNCKA", "target": "7VHGUCIE"}, {"source": "GPPFNCKA", "target": "DNXZWQYC"}, {"source": "GPPFNCKA", "target": "6E5KLX6X"}, {"source": "GPPFNCKA", "target": "RPTF5C6P"}, {"source": "GPPFNCKA", "target": "AUQ4TB89"}, {"source": "5ARGAXD5", "target": "EFF5GF65"}, {"source": "5ARGAXD5", "target": "HL2YSKU9"}, {"source": "5ARGAXD5", "target": "RTTHJN6V"}, {"source": "5ARGAXD5", "target": "NB7I59CD"}, {"source": "5ARGAXD5", "target": "WR44SNW8"}, {"source": "5ARGAXD5", "target": "3ETZFFNS"}, {"source": "5ARGAXD5", "target": "34G9QI8T"}, {"source": "5ARGAXD5", "target": "7MYBEEJL"}, {"source": "5ARGAXD5", "target": "FXISQ7ZW"}, {"source": "5ARGAXD5", "target": "5G4IZVQ8"}, {"source": "5ARGAXD5", "target": "3SN7EBSL"}, {"source": "5ARGAXD5", "target": "DNXZWQYC"}, {"source": "5ARGAXD5", "target": "MFG9C974"}, {"source": "5ARGAXD5", "target": "GVLDYG9U"}, {"source": "5ARGAXD5", "target": "33CHN65F"}, {"source": "5TS8QK22", "target": "EFF5GF65"}, {"source": "5TS8QK22", "target": "PY7VZARY"}, {"source": "5TS8QK22", "target": "2CAC6487"}, {"source": "PY7VZARY", "target": "EFF5GF65"}, {"source": "PY7VZARY", "target": "I5GW9TLE"}, {"source": "PY7VZARY", "target": "A3KYE8IS"}, {"source": "PY7VZARY", "target": "528XYVYW"}, {"source": "PY7VZARY", "target": "EAMLK3Y5"}, {"source": "PY7VZARY", "target": "ARDEEPXR"}, {"source": "PY7VZARY", "target": "RTTHJN6V"}, {"source": "PY7VZARY", "target": "TC9VUUIV"}, {"source": "PY7VZARY", "target": "Y2Y2RI89"}, {"source": "PY7VZARY", "target": "2CGJFSN3"}, {"source": "PY7VZARY", "target": "93EJ6DH8"}, {"source": "PY7VZARY", "target": "C4J4FFM6"}, {"source": "PY7VZARY", "target": "6XE6BCA9"}, {"source": "PY7VZARY", "target": "7LPQ6DBD"}, {"source": "PY7VZARY", "target": "UW3MAL32"}, {"source": "PY7VZARY", "target": "5ARGAXD5"}, {"source": "PY7VZARY", "target": "NZ9HRJ7K"}, {"source": "PY7VZARY", "target": "BE48TX2H"}, {"source": "PY7VZARY", "target": "34G9QI8T"}, {"source": "PY7VZARY", "target": "7MYBEEJL"}, {"source": "PY7VZARY", "target": "3SN7EBSL"}, {"source": "PY7VZARY", "target": "TWSMZCW6"}, {"source": "PY7VZARY", "target": "MFG9C974"}, {"source": "PY7VZARY", "target": "7NYCPT65"}, {"source": "PY7VZARY", "target": "PSKGU9XR"}, {"source": "PY7VZARY", "target": "2KXZIYTT"}, {"source": "PY7VZARY", "target": "V37PB4KM"}, {"source": "PY7VZARY", "target": "H3LYYGZ8"}, {"source": "PY7VZARY", "target": "J5FFLRYZ"}, {"source": "PY7VZARY", "target": "98CK7UFR"}, {"source": "SFKG795G", "target": "EFF5GF65"}, {"source": "SFKG795G", "target": "G73KS8UQ"}, {"source": "SFKG795G", "target": "HYTH7KQ5"}, {"source": "SFKG795G", "target": "C2C72RPF"}, {"source": "SFKG795G", "target": "DNXZWQYC"}, {"source": "SFKG795G", "target": "AD25IKQR"}, {"source": "SFKG795G", "target": "V4RID8TN"}, {"source": "SFKG795G", "target": "3N9XWYFJ"}, {"source": "SFKG795G", "target": "4VVW4E7R"}, {"source": "SFKG795G", "target": "LBRII9F5"}, {"source": "SFKG795G", "target": "YELA7MTZ"}, {"source": "SFKG795G", "target": "SHZBLVNX"}, {"source": "SFKG795G", "target": "ZBR2P2MG"}, {"source": "9BKHBAKQ", "target": "G73KS8UQ"}, {"source": "9BKHBAKQ", "target": "DFHWY9KT"}, {"source": "9BKHBAKQ", "target": "3ETZFFNS"}, {"source": "9BKHBAKQ", "target": "L8NRCZ8E"}, {"source": "9BKHBAKQ", "target": "V4RID8TN"}, {"source": "9BKHBAKQ", "target": "YGSP98R9"}, {"source": "9BKHBAKQ", "target": "LBRII9F5"}, {"source": "9BKHBAKQ", "target": "7QGFCBNH"}, {"source": "IPC36S5V", "target": "G73KS8UQ"}, {"source": "IPC36S5V", "target": "HYTH7KQ5"}, {"source": "IPC36S5V", "target": "GJK38T9U"}, {"source": "IPC36S5V", "target": "AD25IKQR"}, {"source": "IPC36S5V", "target": "V4RID8TN"}, {"source": "IPC36S5V", "target": "3N9XWYFJ"}, {"source": "IPC36S5V", "target": "SFKG795G"}, {"source": "IPC36S5V", "target": "YGSP98R9"}, {"source": "IPC36S5V", "target": "4VVW4E7R"}, {"source": "IPC36S5V", "target": "LS3DVSRL"}, {"source": "IPC36S5V", "target": "LBRII9F5"}, {"source": "IPC36S5V", "target": "YELA7MTZ"}, {"source": "IPC36S5V", "target": "M8IEXC3J"}, {"source": "IPC36S5V", "target": "2KXZIYTT"}, {"source": "TXWCP8I8", "target": "G73KS8UQ"}, {"source": "TXWCP8I8", "target": "E4ZYMDJZ"}, {"source": "TXWCP8I8", "target": "MMP7ENHA"}, {"source": "TXWCP8I8", "target": "GFPD6PFR"}, {"source": "TXWCP8I8", "target": "8VJLICRZ"}, {"source": "TXWCP8I8", "target": "JF88W22K"}, {"source": "TXWCP8I8", "target": "V4RID8TN"}, {"source": "TXWCP8I8", "target": "AR2BHG9K"}, {"source": "TXWCP8I8", "target": "MRQB7B6N"}, {"source": "TXWCP8I8", "target": "IPC36S5V"}, {"source": "TXWCP8I8", "target": "XB6ES2CL"}, {"source": "TXWCP8I8", "target": "ELW3I7GH"}, {"source": "TXWCP8I8", "target": "TXWCP8I8"}, {"source": "ELW3I7GH", "target": "ZRBMFYZM"}, {"source": "ELW3I7GH", "target": "QGBJAIEI"}, {"source": "ELW3I7GH", "target": "9ADQIL25"}, {"source": "ELW3I7GH", "target": "I9WRBFTN"}, {"source": "ELW3I7GH", "target": "34G9QI8T"}, {"source": "ELW3I7GH", "target": "5G4IZVQ8"}, {"source": "ELW3I7GH", "target": "Y4DL944F"}, {"source": "ELW3I7GH", "target": "V4RID8TN"}, {"source": "ELW3I7GH", "target": "3N9XWYFJ"}, {"source": "ELW3I7GH", "target": "83CAPN4G"}, {"source": "ELW3I7GH", "target": "EJENTABB"}, {"source": "ELW3I7GH", "target": "AR2BHG9K"}, {"source": "ELW3I7GH", "target": "Q7HDXF92"}, {"source": "ELW3I7GH", "target": "XB6ES2CL"}, {"source": "ELW3I7GH", "target": "YQWKSHX5"}, {"source": "ELW3I7GH", "target": "7QGFCBNH"}, {"source": "Q7HDXF92", "target": "ZRBMFYZM"}, {"source": "Q7HDXF92", "target": "C3II3FX6"}, {"source": "Q7HDXF92", "target": "7SQSUAJJ"}, {"source": "Q7HDXF92", "target": "HYTH7KQ5"}, {"source": "Q7HDXF92", "target": "KGY9T3MH"}, {"source": "Q7HDXF92", "target": "7WSWWYHM"}, {"source": "Q7HDXF92", "target": "YLP38A4R"}, {"source": "Q7HDXF92", "target": "3N9XWYFJ"}, {"source": "Q7HDXF92", "target": "Q7HDXF92"}, {"source": "Q7HDXF92", "target": "QU7MV362"}, {"source": "66UW8D43", "target": "C3II3FX6"}, {"source": "66UW8D43", "target": "KGY9T3MH"}, {"source": "66UW8D43", "target": "B6CEU5DC"}, {"source": "66UW8D43", "target": "DSQIERIF"}, {"source": "66UW8D43", "target": "7UWQD2V7"}, {"source": "66UW8D43", "target": "KKPRRYF5"}, {"source": "66UW8D43", "target": "UD9ELGDZ"}, {"source": "66UW8D43", "target": "JCSVCM3Q"}, {"source": "66UW8D43", "target": "9G5KE3NB"}, {"source": "66UW8D43", "target": "JHITWF3L"}, {"source": "66UW8D43", "target": "AIHUXYD5"}, {"source": "66UW8D43", "target": "HLGK973Q"}, {"source": "66UW8D43", "target": "VFE2E59A"}, {"source": "66UW8D43", "target": "XI7CYRG8"}, {"source": "66UW8D43", "target": "EXE29BH4"}, {"source": "66UW8D43", "target": "QU7MV362"}, {"source": "66UW8D43", "target": "EFJYEVC6"}, {"source": "66UW8D43", "target": "3CP5KRDI"}, {"source": "WVU5AFQJ", "target": "S68H9QBG"}, {"source": "WVU5AFQJ", "target": "7SQSUAJJ"}, {"source": "WVU5AFQJ", "target": "RTTHJN6V"}, {"source": "WVU5AFQJ", "target": "JQNL2KII"}, {"source": "WVU5AFQJ", "target": "ICGJ5R6J"}, {"source": "WVU5AFQJ", "target": "3N9XWYFJ"}, {"source": "WVU5AFQJ", "target": "U2ZWMF5Q"}, {"source": "WVU5AFQJ", "target": "VFE2E59A"}, {"source": "WVU5AFQJ", "target": "IPC36S5V"}, {"source": "WVU5AFQJ", "target": "Z4KN26RY"}, {"source": "WVU5AFQJ", "target": "SHZBLVNX"}, {"source": "WVU5AFQJ", "target": "ZBR2P2MG"}, {"source": "B6876BD4", "target": "IKKZ8UA9"}, {"source": "B6876BD4", "target": "9TFDXLXF"}, {"source": "B6876BD4", "target": "J9WNBL8A"}, {"source": "B6876BD4", "target": "TWSMZCW6"}, {"source": "B6876BD4", "target": "LIBVLLA2"}, {"source": "B6876BD4", "target": "8FRVH3NK"}, {"source": "B6876BD4", "target": "H9U8VET3"}, {"source": "B6876BD4", "target": "QNEKP2L8"}, {"source": "B6876BD4", "target": "RJF67ZIL"}, {"source": "B6876BD4", "target": "QIAUJG5Q"}, {"source": "B6876BD4", "target": "N8IBRSYQ"}, {"source": "B6876BD4", "target": "MFG9C974"}, {"source": "B6876BD4", "target": "F7ZF6LU6"}, {"source": "B6876BD4", "target": "DXJZBZW7"}, {"source": "B6876BD4", "target": "DGWGMJ7U"}, {"source": "B6876BD4", "target": "GVLDYG9U"}, {"source": "B6876BD4", "target": "PPRISUKF"}, {"source": "B6876BD4", "target": "9NTFAVMI"}, {"source": "DVT2R32N", "target": "MBUJ4A4F"}, {"source": "DVT2R32N", "target": "MYBFDHFH"}, {"source": "DVT2R32N", "target": "3SN7EBSL"}, {"source": "DVT2R32N", "target": "GVLDYG9U"}, {"source": "GVLDYG9U", "target": "6FLUSZNW"}, {"source": "GVLDYG9U", "target": "L7J4LN4B"}, {"source": "GVLDYG9U", "target": "4VSAZ6YN"}, {"source": "GVLDYG9U", "target": "HL2YSKU9"}, {"source": "GVLDYG9U", "target": "7P4X3G4E"}, {"source": "GVLDYG9U", "target": "IJFUF9XC"}, {"source": "GVLDYG9U", "target": "7NYCPT65"}, {"source": "GVLDYG9U", "target": "BMHCIT94"}, {"source": "GVLDYG9U", "target": "MJUHEIIH"}, {"source": "GVLDYG9U", "target": "2DAFRDMY"}, {"source": "GVLDYG9U", "target": "WRCPUI4X"}, {"source": "5G4IZVQ8", "target": "9TFDXLXF"}, {"source": "5G4IZVQ8", "target": "YKC69FSL"}, {"source": "5G4IZVQ8", "target": "RTTHJN6V"}, {"source": "5G4IZVQ8", "target": "TWSMZCW6"}, {"source": "5G4IZVQ8", "target": "LFLTWJAM"}, {"source": "5G4IZVQ8", "target": "VEVPRU6Q"}, {"source": "5G4IZVQ8", "target": "MFG9C974"}, {"source": "5G4IZVQ8", "target": "GVLDYG9U"}, {"source": "LFLTWJAM", "target": "9TFDXLXF"}, {"source": "LFLTWJAM", "target": "PWF27R38"}, {"source": "LFLTWJAM", "target": "NMIGKYKL"}, {"source": "LFLTWJAM", "target": "564YS9JY"}, {"source": "LFLTWJAM", "target": "8B8M8IIT"}, {"source": "LFLTWJAM", "target": "2Q4HVPUJ"}, {"source": "LFLTWJAM", "target": "DJRSCTXM"}, {"source": "LFLTWJAM", "target": "R5QFW2RA"}, {"source": "LFLTWJAM", "target": "2TYDU7YN"}, {"source": "RTTHJN6V", "target": "9TFDXLXF"}, {"source": "RTTHJN6V", "target": "6QHZ3LJG"}, {"source": "RTTHJN6V", "target": "NA5JTD78"}, {"source": "RTTHJN6V", "target": "564YS9JY"}, {"source": "RTTHJN6V", "target": "8B8M8IIT"}, {"source": "RTTHJN6V", "target": "TWSMZCW6"}, {"source": "RTTHJN6V", "target": "VEVPRU6Q"}, {"source": "RTTHJN6V", "target": "GVLDYG9U"}, {"source": "RTTHJN6V", "target": "2TYDU7YN"}, {"source": "RTTHJN6V", "target": "S9VWQ4SW"}, {"source": "RTTHJN6V", "target": "WWUJEPEZ"}, {"source": "TWSMZCW6", "target": "9TFDXLXF"}, {"source": "TWSMZCW6", "target": "J9WNBL8A"}, {"source": "TWSMZCW6", "target": "HL2YSKU9"}, {"source": "TWSMZCW6", "target": "MFG9C974"}, {"source": "TWSMZCW6", "target": "GVLDYG9U"}, {"source": "34G9QI8T", "target": "6QHZ3LJG"}, {"source": "34G9QI8T", "target": "NB7I59CD"}, {"source": "34G9QI8T", "target": "8M42693P"}, {"source": "34G9QI8T", "target": "7MYBEEJL"}, {"source": "34G9QI8T", "target": "FXISQ7ZW"}, {"source": "34G9QI8T", "target": "5G4IZVQ8"}, {"source": "34G9QI8T", "target": "3SN7EBSL"}, {"source": "34G9QI8T", "target": "DNXZWQYC"}, {"source": "34G9QI8T", "target": "TWSMZCW6"}, {"source": "34G9QI8T", "target": "NEY2LB77"}, {"source": "34G9QI8T", "target": "33CHN65F"}, {"source": "93EJ6DH8", "target": "I5GW9TLE"}, {"source": "93EJ6DH8", "target": "TC9VUUIV"}, {"source": "93EJ6DH8", "target": "NX46SKFP"}, {"source": "93EJ6DH8", "target": "C4J4FFM6"}, {"source": "93EJ6DH8", "target": "UW3MAL32"}, {"source": "93EJ6DH8", "target": "Z7W3DR4J"}, {"source": "93EJ6DH8", "target": "BE48TX2H"}, {"source": "93EJ6DH8", "target": "3SN7EBSL"}, {"source": "93EJ6DH8", "target": "MJUHEIIH"}, {"source": "93EJ6DH8", "target": "GVLDYG9U"}, {"source": "93EJ6DH8", "target": "7QK5BNAN"}, {"source": "93EJ6DH8", "target": "T4KFKLRI"}, {"source": "93EJ6DH8", "target": "TCRGLTG2"}, {"source": "93EJ6DH8", "target": "IXZCFH88"}, {"source": "93EJ6DH8", "target": "EM9JCYAZ"}, {"source": "93EJ6DH8", "target": "J5FFLRYZ"}, {"source": "NX46SKFP", "target": "I5GW9TLE"}, {"source": "NX46SKFP", "target": "TC9VUUIV"}, {"source": "NX46SKFP", "target": "UW3MAL32"}, {"source": "NX46SKFP", "target": "Z7W3DR4J"}, {"source": "NX46SKFP", "target": "BE48TX2H"}, {"source": "NX46SKFP", "target": "3SN7EBSL"}, {"source": "NX46SKFP", "target": "TWSMZCW6"}, {"source": "NX46SKFP", "target": "E5UC3428"}, {"source": "NX46SKFP", "target": "F7ZF6LU6"}, {"source": "NX46SKFP", "target": "3S7J23W4"}, {"source": "NX46SKFP", "target": "IXZCFH88"}, {"source": "NX46SKFP", "target": "HEN6HS4C"}, {"source": "NX46SKFP", "target": "EM9JCYAZ"}, {"source": "7L8LVZG6", "target": "YKC69FSL"}, {"source": "7L8LVZG6", "target": "F7ZF6LU6"}, {"source": "HL2YSKU9", "target": "YKC69FSL"}, {"source": "HL2YSKU9", "target": "R2R8K52A"}, {"source": "HL2YSKU9", "target": "797YFL9B"}, {"source": "HL2YSKU9", "target": "9XMFRZKL"}, {"source": "HL2YSKU9", "target": "528XYVYW"}, {"source": "HL2YSKU9", "target": "DJK49L3D"}, {"source": "HL2YSKU9", "target": "2Q7TUF99"}, {"source": "HL2YSKU9", "target": "NMIGKYKL"}, {"source": "HL2YSKU9", "target": "MDBVTAH7"}, {"source": "HL2YSKU9", "target": "KB955BFR"}, {"source": "HL2YSKU9", "target": "NVG3SRJ4"}, {"source": "HL2YSKU9", "target": "J9WNBL8A"}, {"source": "HL2YSKU9", "target": "564YS9JY"}, {"source": "HL2YSKU9", "target": "VTK2L8MK"}, {"source": "HL2YSKU9", "target": "FHXYQJ5A"}, {"source": "HL2YSKU9", "target": "4I95LEVG"}, {"source": "HL2YSKU9", "target": "TRN2VFVL"}, {"source": "HL2YSKU9", "target": "82SWVH2E"}, {"source": "A4ZPDKMT", "target": "CC5FSKP9"}, {"source": "98CK7UFR", "target": "A3KYE8IS"}, {"source": "TC9VUUIV", "target": "W7IDCXT4"}, {"source": "TC9VUUIV", "target": "3ETZFFNS"}, {"source": "TC9VUUIV", "target": "7MYBEEJL"}, {"source": "TC9VUUIV", "target": "THS8SVYY"}, {"source": "TC9VUUIV", "target": "E5UC3428"}, {"source": "TC9VUUIV", "target": "V37PB4KM"}, {"source": "TC9VUUIV", "target": "EBUAS4W8"}, {"source": "TC9VUUIV", "target": "XKFR78UH"}, {"source": "2CGJFSN3", "target": "ELI78EZX"}, {"source": "2CGJFSN3", "target": "RTTHJN6V"}, {"source": "2CGJFSN3", "target": "7MYBEEJL"}, {"source": "2CGJFSN3", "target": "5G4IZVQ8"}, {"source": "2CGJFSN3", "target": "3SN7EBSL"}, {"source": "2CGJFSN3", "target": "TWSMZCW6"}, {"source": "2CGJFSN3", "target": "33CHN65F"}, {"source": "U8JKUGA8", "target": "ELI78EZX"}, {"source": "U8JKUGA8", "target": "3ETZFFNS"}, {"source": "U8JKUGA8", "target": "YGRIWHW4"}, {"source": "2CAC6487", "target": "WKK56EXU"}, {"source": "2CAC6487", "target": "EAMLK3Y5"}, {"source": "2CAC6487", "target": "Y2Y2RI89"}, {"source": "2CAC6487", "target": "PY7VZARY"}, {"source": "2CAC6487", "target": "JQNL2KII"}, {"source": "2CAC6487", "target": "BE48TX2H"}, {"source": "2CAC6487", "target": "IIM9QZV9"}, {"source": "2CAC6487", "target": "NTUWGCDT"}, {"source": "2CAC6487", "target": "6E5KLX6X"}, {"source": "2CAC6487", "target": "PSKGU9XR"}, {"source": "2CAC6487", "target": "LRZJZVPL"}, {"source": "HLGK973Q", "target": "F9HV5EF8"}, {"source": "HLGK973Q", "target": "692FHSHH"}, {"source": "HLGK973Q", "target": "4VSAZ6YN"}, {"source": "HLGK973Q", "target": "3MS4DDA9"}, {"source": "HLGK973Q", "target": "93EJ6DH8"}, {"source": "HLGK973Q", "target": "NX46SKFP"}, {"source": "HLGK973Q", "target": "EG5CF9XD"}, {"source": "HLGK973Q", "target": "2CAC6487"}, {"source": "HLGK973Q", "target": "ASVT2FM6"}, {"source": "HLGK973Q", "target": "JQNL2KII"}, {"source": "HLGK973Q", "target": "3SN7EBSL"}, {"source": "HLGK973Q", "target": "NVKR6U7A"}, {"source": "HLGK973Q", "target": "LXMLAZEY"}, {"source": "HLGK973Q", "target": "GVLDYG9U"}, {"source": "HLGK973Q", "target": "4VVW4E7R"}, {"source": "HLGK973Q", "target": "PN4KZW88"}, {"source": "HLGK973Q", "target": "J5FFLRYZ"}, {"source": "HLGK973Q", "target": "A5GC3I4X"}, {"source": "HLGK973Q", "target": "7CIQ9LTV"}, {"source": "HLGK973Q", "target": "ADK3L4K5"}, {"source": "M8IEXC3J", "target": "HYTH7KQ5"}, {"source": "M8IEXC3J", "target": "GVLDYG9U"}, {"source": "M8IEXC3J", "target": "7WSWWYHM"}, {"source": "M8IEXC3J", "target": "YLP38A4R"}, {"source": "M8IEXC3J", "target": "HLGK973Q"}, {"source": "M8IEXC3J", "target": "YGSP98R9"}, {"source": "M8IEXC3J", "target": "4VVW4E7R"}, {"source": "M8IEXC3J", "target": "LBRII9F5"}, {"source": "M8IEXC3J", "target": "PN4KZW88"}, {"source": "EXE29BH4", "target": "KGY9T3MH"}, {"source": "EXE29BH4", "target": "Q3LGUB6S"}, {"source": "EXE29BH4", "target": "9ADQIL25"}, {"source": "EXE29BH4", "target": "GJK38T9U"}, {"source": "EXE29BH4", "target": "2CAC6487"}, {"source": "EXE29BH4", "target": "6SUNA9ZC"}, {"source": "EXE29BH4", "target": "AIHUXYD5"}, {"source": "EXE29BH4", "target": "U28W6G7H"}, {"source": "EXE29BH4", "target": "AN4VBEKF"}, {"source": "EXE29BH4", "target": "LJZB6MTP"}, {"source": "EXE29BH4", "target": "VFE2E59A"}, {"source": "EXE29BH4", "target": "DN3YBFQM"}, {"source": "EXE29BH4", "target": "QU7MV362"}, {"source": "EXE29BH4", "target": "M8IEXC3J"}, {"source": "EXE29BH4", "target": "ZBCN7AQW"}, {"source": "EXE29BH4", "target": "J7JUTEAB"}, {"source": "J7JUTEAB", "target": "KGY9T3MH"}, {"source": "J7JUTEAB", "target": "Q3LGUB6S"}, {"source": "J7JUTEAB", "target": "JW4WDRBE"}, {"source": "J7JUTEAB", "target": "C4J4FFM6"}, {"source": "J7JUTEAB", "target": "2CAC6487"}, {"source": "J7JUTEAB", "target": "3IKXM4X7"}, {"source": "J7JUTEAB", "target": "6SUNA9ZC"}, {"source": "J7JUTEAB", "target": "LXMLAZEY"}, {"source": "J7JUTEAB", "target": "PR2LV2XL"}, {"source": "J7JUTEAB", "target": "U28W6G7H"}, {"source": "J7JUTEAB", "target": "LJZB6MTP"}, {"source": "J7JUTEAB", "target": "TR6PDBUB"}, {"source": "J7JUTEAB", "target": "Q7HDXF92"}, {"source": "J7JUTEAB", "target": "DN3YBFQM"}, {"source": "J7JUTEAB", "target": "QU7MV362"}, {"source": "J7JUTEAB", "target": "XB6ES2CL"}, {"source": "J7JUTEAB", "target": "M8IEXC3J"}, {"source": "J7JUTEAB", "target": "ZBCN7AQW"}, {"source": "QU7MV362", "target": "KGY9T3MH"}, {"source": "QU7MV362", "target": "F2L78HEX"}, {"source": "QU7MV362", "target": "PR2LV2XL"}, {"source": "QU7MV362", "target": "U28W6G7H"}, {"source": "QU7MV362", "target": "VFE2E59A"}, {"source": "QU7MV362", "target": "DN3YBFQM"}, {"source": "QU7MV362", "target": "ZBCN7AQW"}, {"source": "GJHWZHKJ", "target": "Q3LGUB6S"}, {"source": "GJHWZHKJ", "target": "42IDCQHX"}, {"source": "GJHWZHKJ", "target": "RS5DBPDD"}, {"source": "GJHWZHKJ", "target": "AN4VBEKF"}, {"source": "GJHWZHKJ", "target": "RB4Y9E6M"}, {"source": "U28W6G7H", "target": "JW4WDRBE"}, {"source": "U28W6G7H", "target": "UIL72SAR"}, {"source": "U28W6G7H", "target": "C4J4FFM6"}, {"source": "U28W6G7H", "target": "HLGK973Q"}, {"source": "U28W6G7H", "target": "M8IEXC3J"}, {"source": "ZBCN7AQW", "target": "JW4WDRBE"}, {"source": "ZBCN7AQW", "target": "VFE2E59A"}, {"source": "ZBCN7AQW", "target": "DN3YBFQM"}, {"source": "ZBCN7AQW", "target": "LS3DVSRL"}, {"source": "37DD97CJ", "target": "AJ6Q3HEV"}, {"source": "37DD97CJ", "target": "CH2I4QZD"}, {"source": "37DD97CJ", "target": "KTXFLPM3"}, {"source": "37DD97CJ", "target": "4VSAZ6YN"}, {"source": "37DD97CJ", "target": "4K9QM67N"}, {"source": "37DD97CJ", "target": "3SN7EBSL"}, {"source": "37DD97CJ", "target": "DXJZBZW7"}, {"source": "37DD97CJ", "target": "DGWGMJ7U"}, {"source": "37DD97CJ", "target": "GVLDYG9U"}, {"source": "37DD97CJ", "target": "TF258FMY"}, {"source": "37DD97CJ", "target": "WWUJEPEZ"}, {"source": "GPFCVH4W", "target": "DSQIERIF"}, {"source": "GPFCVH4W", "target": "JF88W22K"}, {"source": "GPFCVH4W", "target": "RTTHJN6V"}, {"source": "GPFCVH4W", "target": "C4J4FFM6"}, {"source": "GPFCVH4W", "target": "EG5CF9XD"}, {"source": "GPFCVH4W", "target": "2CAC6487"}, {"source": "GPFCVH4W", "target": "JQNL2KII"}, {"source": "GPFCVH4W", "target": "3SN7EBSL"}, {"source": "GPFCVH4W", "target": "C6YPQLJI"}, {"source": "GPFCVH4W", "target": "GVLDYG9U"}, {"source": "GPFCVH4W", "target": "BG32MCY5"}, {"source": "GPFCVH4W", "target": "H4FC77LT"}, {"source": "GPFCVH4W", "target": "AD25IKQR"}, {"source": "GPFCVH4W", "target": "HLGK973Q"}, {"source": "GPFCVH4W", "target": "FQTXYHMF"}, {"source": "GPFCVH4W", "target": "C44N7NAR"}, {"source": "GPFCVH4W", "target": "WD6EIVIV"}, {"source": "GPFCVH4W", "target": "MRQB7B6N"}, {"source": "GPFCVH4W", "target": "VFE2E59A"}, {"source": "GPFCVH4W", "target": "TR6PDBUB"}, {"source": "GPFCVH4W", "target": "EXE29BH4"}, {"source": "GPFCVH4W", "target": "DN3YBFQM"}, {"source": "GPFCVH4W", "target": "QU7MV362"}, {"source": "GPFCVH4W", "target": "EFJYEVC6"}, {"source": "GPFCVH4W", "target": "66UW8D43"}, {"source": "GPFCVH4W", "target": "ZBCN7AQW"}, {"source": "GPFCVH4W", "target": "J7JUTEAB"}, {"source": "GPFCVH4W", "target": "HS2MRUCX"}, {"source": "GPFCVH4W", "target": "ZBR2P2MG"}, {"source": "GPFCVH4W", "target": "7CIQ9LTV"}, {"source": "GPFCVH4W", "target": "LCV9X2XP"}, {"source": "GPFCVH4W", "target": "ADK3L4K5"}, {"source": "GPFCVH4W", "target": "7QGFCBNH"}, {"source": "F7ZF6LU6", "target": "PKYAFZ33"}, {"source": "F7ZF6LU6", "target": "R2R8K52A"}, {"source": "F7ZF6LU6", "target": "5ZFM6G5S"}, {"source": "F7ZF6LU6", "target": "Q586T6MR"}, {"source": "66NTNCWL", "target": "CH2I4QZD"}, {"source": "66NTNCWL", "target": "NMIGKYKL"}, {"source": "66NTNCWL", "target": "JJMULJ8U"}, {"source": "66NTNCWL", "target": "8B8M8IIT"}, {"source": "97Z5KABU", "target": "3UYN3NA3"}, {"source": "97Z5KABU", "target": "ZTDFG5IT"}, {"source": "97Z5KABU", "target": "WPVJ7BMX"}, {"source": "97Z5KABU", "target": "RC5KRZCD"}, {"source": "97Z5KABU", "target": "PWF27R38"}, {"source": "97Z5KABU", "target": "4595RUZ3"}, {"source": "97Z5KABU", "target": "NL9QRJ8A"}, {"source": "97Z5KABU", "target": "M3MI9IHT"}, {"source": "97Z5KABU", "target": "CTE2JETU"}, {"source": "97Z5KABU", "target": "YNKK75LQ"}, {"source": "97Z5KABU", "target": "VDBZSK5N"}, {"source": "97Z5KABU", "target": "4RC9LPI4"}, {"source": "97Z5KABU", "target": "43VL8TVM"}, {"source": "97Z5KABU", "target": "GMXY7BWK"}, {"source": "97Z5KABU", "target": "VJ66H9QC"}, {"source": "97Z5KABU", "target": "BLZ4M3Y4"}, {"source": "97Z5KABU", "target": "DM8JRXL3"}, {"source": "97Z5KABU", "target": "JTYEPD92"}, {"source": "RPTF5C6P", "target": "C2C72RPF"}, {"source": "RPTF5C6P", "target": "NA83BBQ9"}, {"source": "RPTF5C6P", "target": "2CAC6487"}, {"source": "RPTF5C6P", "target": "UW3MAL32"}, {"source": "RPTF5C6P", "target": "WR44SNW8"}, {"source": "RPTF5C6P", "target": "5ARGAXD5"}, {"source": "RPTF5C6P", "target": "JQNL2KII"}, {"source": "RPTF5C6P", "target": "YKFJBKEF"}, {"source": "RPTF5C6P", "target": "5G4IZVQ8"}, {"source": "RPTF5C6P", "target": "3SN7EBSL"}, {"source": "RPTF5C6P", "target": "E5UC3428"}, {"source": "RPTF5C6P", "target": "EWUU64GR"}, {"source": "RPTF5C6P", "target": "LCV9X2XP"}, {"source": "Z7W3DR4J", "target": "C2C72RPF"}, {"source": "Z7W3DR4J", "target": "UW3MAL32"}, {"source": "Z7W3DR4J", "target": "DNXZWQYC"}, {"source": "Z7W3DR4J", "target": "MFG9C974"}, {"source": "VWBGJGAL", "target": "ZTDFG5IT"}, {"source": "VWBGJGAL", "target": "HRRMJZ7P"}, {"source": "VWBGJGAL", "target": "DJK49L3D"}, {"source": "VWBGJGAL", "target": "L4A8867M"}, {"source": "VWBGJGAL", "target": "D3IMH8QU"}, {"source": "VWBGJGAL", "target": "PWF27R38"}, {"source": "VWBGJGAL", "target": "3CK55IK5"}, {"source": "VWBGJGAL", "target": "NL9QRJ8A"}, {"source": "VWBGJGAL", "target": "IZKMXT27"}, {"source": "VWBGJGAL", "target": "WZNRVQ38"}, {"source": "VWBGJGAL", "target": "CWKWIWG4"}, {"source": "VWBGJGAL", "target": "M3MI9IHT"}, {"source": "VWBGJGAL", "target": "CN8X5IJB"}, {"source": "VWBGJGAL", "target": "Z9KG6CD6"}, {"source": "VWBGJGAL", "target": "XH58TNLL"}, {"source": "VWBGJGAL", "target": "3RP9NCHT"}, {"source": "VWBGJGAL", "target": "TU2VIQQY"}, {"source": "VWBGJGAL", "target": "L8IYN5ZP"}, {"source": "VWBGJGAL", "target": "UPZYZLJQ"}, {"source": "6PCTX6BW", "target": "AYBC8NT2"}, {"source": "6PCTX6BW", "target": "C4J4FFM6"}, {"source": "6PCTX6BW", "target": "3FP23RSV"}, {"source": "6PCTX6BW", "target": "4VVW4E7R"}, {"source": "6PCTX6BW", "target": "ADK3L4K5"}, {"source": "6PCTX6BW", "target": "7QGFCBNH"}, {"source": "6PCTX6BW", "target": "Q473REEE"}, {"source": "I55QRACV", "target": "MYJM3I6X"}, {"source": "I55QRACV", "target": "5J8BBLUH"}, {"source": "I55QRACV", "target": "AN4VBEKF"}, {"source": "I55QRACV", "target": "XSVIIP5L"}, {"source": "I55QRACV", "target": "FQTXYHMF"}, {"source": "I55QRACV", "target": "GJHWZHKJ"}, {"source": "I55QRACV", "target": "ELW3I7GH"}, {"source": "I55QRACV", "target": "YQWKSHX5"}, {"source": "I55QRACV", "target": "M8IEXC3J"}, {"source": "BE48TX2H", "target": "5ZFM6G5S"}, {"source": "BE48TX2H", "target": "6XE6BCA9"}, {"source": "BE48TX2H", "target": "NZ9HRJ7K"}, {"source": "BE48TX2H", "target": "BE48TX2H"}, {"source": "BE48TX2H", "target": "3SN7EBSL"}, {"source": "BE48TX2H", "target": "B6876BD4"}, {"source": "YQ7GHGC3", "target": "9ADQIL25"}, {"source": "YQ7GHGC3", "target": "5PSQ97GL"}, {"source": "YQ7GHGC3", "target": "ZYA68N2R"}, {"source": "YQ7GHGC3", "target": "TC9VUUIV"}, {"source": "YQ7GHGC3", "target": "C4J4FFM6"}, {"source": "YQ7GHGC3", "target": "VR4FDYCU"}, {"source": "YQ7GHGC3", "target": "97Q2YYXG"}, {"source": "YQ7GHGC3", "target": "Z8YNTPTS"}, {"source": "YQ7GHGC3", "target": "PR2LV2XL"}, {"source": "YQ7GHGC3", "target": "C44N7NAR"}, {"source": "YQ7GHGC3", "target": "Q7HDXF92"}, {"source": "YQ7GHGC3", "target": "EXE29BH4"}, {"source": "YQ7GHGC3", "target": "QU7MV362"}, {"source": "YQ7GHGC3", "target": "66UW8D43"}, {"source": "YQ7GHGC3", "target": "TXWCP8I8"}, {"source": "YQ7GHGC3", "target": "J7JUTEAB"}, {"source": "YQ7GHGC3", "target": "3CP5KRDI"}, {"source": "H4FC77LT", "target": "A9Z3IL6G"}, {"source": "H4FC77LT", "target": "KV8PHWTV"}, {"source": "H4FC77LT", "target": "W3N99HTI"}, {"source": "H4FC77LT", "target": "7CIQ9LTV"}, {"source": "H4FC77LT", "target": "ADK3L4K5"}, {"source": "YQWKSHX5", "target": "9EEKDMCQ"}, {"source": "YQWKSHX5", "target": "EAMLK3Y5"}, {"source": "YQWKSHX5", "target": "AD25IKQR"}, {"source": "YQWKSHX5", "target": "RS5DBPDD"}, {"source": "YQWKSHX5", "target": "EJENTABB"}, {"source": "YQWKSHX5", "target": "AN4VBEKF"}, {"source": "YQWKSHX5", "target": "LBRII9F5"}, {"source": "YQWKSHX5", "target": "ZBR2P2MG"}, {"source": "YQWKSHX5", "target": "7QGFCBNH"}, {"source": "CEDN8EB5", "target": "3SSXIPXK"}, {"source": "CEDN8EB5", "target": "9M6RQUA9"}, {"source": "CEDN8EB5", "target": "RZQZTZRG"}, {"source": "CEDN8EB5", "target": "HME9T53M"}, {"source": "CEDN8EB5", "target": "3V2PBUQN"}, {"source": "CEDN8EB5", "target": "WRS4B94R"}, {"source": "CEDN8EB5", "target": "N7T4ZT8C"}, {"source": "CEDN8EB5", "target": "7QGFCBNH"}, {"source": "Q473REEE", "target": "BHE2434I"}, {"source": "Q473REEE", "target": "2CAC6487"}, {"source": "Q473REEE", "target": "ASVT2FM6"}, {"source": "Q473REEE", "target": "JQNL2KII"}, {"source": "Q473REEE", "target": "YKFJBKEF"}, {"source": "Q473REEE", "target": "NTUWGCDT"}, {"source": "Q473REEE", "target": "NEY2LB77"}, {"source": "Q473REEE", "target": "RPTF5C6P"}, {"source": "Q473REEE", "target": "4AR6Z52H"}, {"source": "YKFJBKEF", "target": "WPVJ7BMX"}, {"source": "YKFJBKEF", "target": "M3MI9IHT"}, {"source": "YKFJBKEF", "target": "UW3MAL32"}, {"source": "YKFJBKEF", "target": "5ARGAXD5"}, {"source": "YKFJBKEF", "target": "3SN7EBSL"}, {"source": "YKFJBKEF", "target": "NDBBXSFX"}, {"source": "YKFJBKEF", "target": "NEY2LB77"}, {"source": "YKFJBKEF", "target": "97Z5KABU"}, {"source": "YKFJBKEF", "target": "LKW5ARUX"}, {"source": "YKFJBKEF", "target": "RV42EVAU"}, {"source": "ERW4A5K3", "target": "UMG9ZHNR"}, {"source": "ERW4A5K3", "target": "7UEWRDBF"}, {"source": "ERW4A5K3", "target": "298BNUC8"}, {"source": "ERW4A5K3", "target": "9FY2LAJF"}, {"source": "ERW4A5K3", "target": "CUW3YJPW"}, {"source": "ERW4A5K3", "target": "U8TX647F"}, {"source": "ERW4A5K3", "target": "4E4DALCD"}, {"source": "ERW4A5K3", "target": "WXVT9IWS"}, {"source": "ERW4A5K3", "target": "YRG6ESN4"}, {"source": "ERW4A5K3", "target": "874N6QHD"}, {"source": "6XE6BCA9", "target": "528XYVYW"}, {"source": "6XE6BCA9", "target": "37DD97CJ"}, {"source": "6XE6BCA9", "target": "7MYBEEJL"}, {"source": "6XE6BCA9", "target": "3SN7EBSL"}, {"source": "6XE6BCA9", "target": "F7ZF6LU6"}, {"source": "6XE6BCA9", "target": "DXJZBZW7"}, {"source": "6XE6BCA9", "target": "GVLDYG9U"}, {"source": "6XE6BCA9", "target": "2FF2WT72"}, {"source": "7NYCPT65", "target": "528XYVYW"}, {"source": "7NYCPT65", "target": "EXM5QBAL"}, {"source": "NZ9HRJ7K", "target": "528XYVYW"}, {"source": "NZ9HRJ7K", "target": "TZGEUNEC"}, {"source": "NZ9HRJ7K", "target": "6XE6BCA9"}, {"source": "NZ9HRJ7K", "target": "7LPQ6DBD"}, {"source": "NZ9HRJ7K", "target": "EG5CF9XD"}, {"source": "NZ9HRJ7K", "target": "3SN7EBSL"}, {"source": "NZ9HRJ7K", "target": "DXJZBZW7"}, {"source": "NZ9HRJ7K", "target": "8SCKG23G"}, {"source": "NZ9HRJ7K", "target": "2FF2WT72"}, {"source": "8B66GEM2", "target": "D3IMH8QU"}, {"source": "2TYDU7YN", "target": "NMIGKYKL"}, {"source": "2TYDU7YN", "target": "564YS9JY"}, {"source": "NMIGKYKL", "target": "GJ9R7DKV"}, {"source": "8B8M8IIT", "target": "NMIGKYKL"}, {"source": "8M42693P", "target": "NMIGKYKL"}, {"source": "8M42693P", "target": "JJMULJ8U"}, {"source": "8M42693P", "target": "8B8M8IIT"}, {"source": "8M42693P", "target": "5G4IZVQ8"}, {"source": "8M42693P", "target": "3SN7EBSL"}, {"source": "8M42693P", "target": "GVLDYG9U"}, {"source": "8M42693P", "target": "66NTNCWL"}, {"source": "JJMULJ8U", "target": "NMIGKYKL"}, {"source": "JJMULJ8U", "target": "8B8M8IIT"}, {"source": "JJMULJ8U", "target": "LFLTWJAM"}, {"source": "JJMULJ8U", "target": "2TYDU7YN"}, {"source": "33CHN65F", "target": "IZKMXT27"}, {"source": "33CHN65F", "target": "CWKWIWG4"}, {"source": "33CHN65F", "target": "S9VWQ4SW"}, {"source": "33CHN65F", "target": "TU2VIQQY"}, {"source": "33CHN65F", "target": "RJRWMPZC"}, {"source": "33CHN65F", "target": "U698CFBR"}, {"source": "33CHN65F", "target": "STVECQYK"}, {"source": "33CHN65F", "target": "8EZM6ZYV"}, {"source": "33CHN65F", "target": "QM5ZNYQN"}, {"source": "33CHN65F", "target": "NM3SGS4X"}, {"source": "33CHN65F", "target": "PVGTI83X"}, {"source": "FXISQ7ZW", "target": "IZKMXT27"}, {"source": "FXISQ7ZW", "target": "CWKWIWG4"}, {"source": "FXISQ7ZW", "target": "RTTHJN6V"}, {"source": "FXISQ7ZW", "target": "S9VWQ4SW"}, {"source": "FXISQ7ZW", "target": "T2QMJHUW"}, {"source": "FXISQ7ZW", "target": "8EZM6ZYV"}, {"source": "FXISQ7ZW", "target": "NM3SGS4X"}, {"source": "FXISQ7ZW", "target": "33CHN65F"}, {"source": "7LPQ6DBD", "target": "HL2YSKU9"}, {"source": "7LPQ6DBD", "target": "RTTHJN6V"}, {"source": "7LPQ6DBD", "target": "6XE6BCA9"}, {"source": "7LPQ6DBD", "target": "GVLDYG9U"}, {"source": "MFG9C974", "target": "HL2YSKU9"}, {"source": "MFG9C974", "target": "8B66GEM2"}, {"source": "MFG9C974", "target": "7PEDCTSP"}, {"source": "WWUJEPEZ", "target": "M3MI9IHT"}, {"source": "WWUJEPEZ", "target": "LKW5ARUX"}, {"source": "WWUJEPEZ", "target": "MFG9C974"}, {"source": "WWUJEPEZ", "target": "F7ZF6LU6"}, {"source": "WWUJEPEZ", "target": "DXJZBZW7"}, {"source": "WWUJEPEZ", "target": "GVLDYG9U"}, {"source": "WWUJEPEZ", "target": "B6876BD4"}, {"source": "7MYBEEJL", "target": "RTTHJN6V"}, {"source": "7MYBEEJL", "target": "5G4IZVQ8"}, {"source": "7MYBEEJL", "target": "3SN7EBSL"}, {"source": "7MYBEEJL", "target": "TWSMZCW6"}, {"source": "7MYBEEJL", "target": "33CHN65F"}, {"source": "63SCT62K", "target": "RTTHJN6V"}, {"source": "63SCT62K", "target": "5G4IZVQ8"}, {"source": "63SCT62K", "target": "3SN7EBSL"}, {"source": "63SCT62K", "target": "MFG9C974"}, {"source": "63SCT62K", "target": "GVLDYG9U"}, {"source": "63SCT62K", "target": "B6876BD4"}, {"source": "AGD66LJC", "target": "RTTHJN6V"}, {"source": "AGD66LJC", "target": "7MYBEEJL"}, {"source": "Y2Y2RI89", "target": "RTTHJN6V"}, {"source": "Y2Y2RI89", "target": "TC9VUUIV"}, {"source": "Y2Y2RI89", "target": "C4J4FFM6"}, {"source": "Y2Y2RI89", "target": "7MYBEEJL"}, {"source": "Y2Y2RI89", "target": "UAW9VMWX"}, {"source": "Y2Y2RI89", "target": "ZVE482RF"}, {"source": "NB7I59CD", "target": "7N4BYR84"}, {"source": "EJDM67E3", "target": "NB7I59CD"}, {"source": "EJDM67E3", "target": "N9CJVIAZ"}, {"source": "EJDM67E3", "target": "XB78ZGFK"}, {"source": "EJDM67E3", "target": "37QKRIYC"}, {"source": "EJDM67E3", "target": "34G9QI8T"}, {"source": "C4J4FFM6", "target": "TC9VUUIV"}, {"source": "C4J4FFM6", "target": "NX46SKFP"}, {"source": "C4J4FFM6", "target": "6XE6BCA9"}, {"source": "C4J4FFM6", "target": "BE48TX2H"}, {"source": "C4J4FFM6", "target": "TWSMZCW6"}, {"source": "C4J4FFM6", "target": "E5UC3428"}, {"source": "C4J4FFM6", "target": "EBUAS4W8"}, {"source": "C4J4FFM6", "target": "7QK5BNAN"}, {"source": "D7DMRPV2", "target": "TC9VUUIV"}, {"source": "D7DMRPV2", "target": "Y2Y2RI89"}, {"source": "D7DMRPV2", "target": "PY7VZARY"}, {"source": "D7DMRPV2", "target": "C4J4FFM6"}, {"source": "D7DMRPV2", "target": "2CAC6487"}, {"source": "D7DMRPV2", "target": "3ETZFFNS"}, {"source": "D7DMRPV2", "target": "JQNL2KII"}, {"source": "D7DMRPV2", "target": "3IKXM4X7"}, {"source": "D7DMRPV2", "target": "IIM9QZV9"}, {"source": "NA83BBQ9", "target": "Y2Y2RI89"}, {"source": "NA83BBQ9", "target": "5NAEA23U"}, {"source": "NA83BBQ9", "target": "I9WRBFTN"}, {"source": "NA83BBQ9", "target": "2CGJFSN3"}, {"source": "NA83BBQ9", "target": "93EJ6DH8"}, {"source": "NA83BBQ9", "target": "C4J4FFM6"}, {"source": "NA83BBQ9", "target": "UW3MAL32"}, {"source": "NA83BBQ9", "target": "ZVE482RF"}, {"source": "NA83BBQ9", "target": "2KXZIYTT"}, {"source": "IIM9QZV9", "target": "PY7VZARY"}, {"source": "IIM9QZV9", "target": "U8JKUGA8"}, {"source": "IIM9QZV9", "target": "JQNL2KII"}, {"source": "IIM9QZV9", "target": "3IKXM4X7"}, {"source": "IIM9QZV9", "target": "NZ9HRJ7K"}, {"source": "IIM9QZV9", "target": "UAW9VMWX"}, {"source": "IIM9QZV9", "target": "RNI76T8X"}, {"source": "EWUU64GR", "target": "NA83BBQ9"}, {"source": "EWUU64GR", "target": "UW3MAL32"}, {"source": "5NAEA23U", "target": "WR44SNW8"}, {"source": "5NAEA23U", "target": "7N4BYR84"}, {"source": "5NAEA23U", "target": "34G9QI8T"}, {"source": "5NAEA23U", "target": "THS8SVYY"}, {"source": "5NAEA23U", "target": "74K4782Q"}, {"source": "5NAEA23U", "target": "5UEP6FJF"}, {"source": "5NAEA23U", "target": "2KXZIYTT"}, {"source": "I9WRBFTN", "target": "5NAEA23U"}, {"source": "I9WRBFTN", "target": "7MYBEEJL"}, {"source": "I9WRBFTN", "target": "5G4IZVQ8"}, {"source": "I9WRBFTN", "target": "Y4DL944F"}, {"source": "I9WRBFTN", "target": "THS8SVYY"}, {"source": "I9WRBFTN", "target": "KGZ6UCQL"}, {"source": "I9WRBFTN", "target": "YGRIWHW4"}, {"source": "I9WRBFTN", "target": "5UEP6FJF"}, {"source": "I9WRBFTN", "target": "2KXZIYTT"}, {"source": "SHZBLVNX", "target": "I9WRBFTN"}, {"source": "SHZBLVNX", "target": "7MYBEEJL"}, {"source": "EXENA72Y", "target": "C4J4FFM6"}, {"source": "EXENA72Y", "target": "EG5CF9XD"}, {"source": "EXENA72Y", "target": "2CAC6487"}, {"source": "EXENA72Y", "target": "JQNL2KII"}, {"source": "EXENA72Y", "target": "NTUWGCDT"}, {"source": "EXENA72Y", "target": "GVLDYG9U"}, {"source": "EXENA72Y", "target": "RPTF5C6P"}, {"source": "HS2MRUCX", "target": "EG5CF9XD"}, {"source": "HS2MRUCX", "target": "2LDNCRN4"}, {"source": "HS2MRUCX", "target": "V37PB4KM"}, {"source": "AUQ4TB89", "target": "2CAC6487"}, {"source": "AUQ4TB89", "target": "JQNL2KII"}, {"source": "MSXD2NSV", "target": "2CAC6487"}, {"source": "MSXD2NSV", "target": "GVLDYG9U"}, {"source": "PN4KZW88", "target": "2CAC6487"}, {"source": "PN4KZW88", "target": "JQNL2KII"}, {"source": "PN4KZW88", "target": "LXMLAZEY"}, {"source": "PN4KZW88", "target": "4VVW4E7R"}, {"source": "PN4KZW88", "target": "7CIQ9LTV"}, {"source": "PN4KZW88", "target": "LCV9X2XP"}, {"source": "PN4KZW88", "target": "RPTF5C6P"}, {"source": "PN4KZW88", "target": "AUQ4TB89"}, {"source": "PN4KZW88", "target": "ADK3L4K5"}, {"source": "PN4KZW88", "target": "Q473REEE"}, {"source": "PN4KZW88", "target": "EXENA72Y"}, {"source": "UW3MAL32", "target": "3ETZFFNS"}, {"source": "UW3MAL32", "target": "5ARGAXD5"}, {"source": "UW3MAL32", "target": "3SN7EBSL"}, {"source": "7VHGUCIE", "target": "DNXZWQYC"}, {"source": "UAW9VMWX", "target": "3ETZFFNS"}, {"source": "UAW9VMWX", "target": "U8JKUGA8"}, {"source": "QRCNLMFC", "target": "63SCT62K"}, {"source": "XI7CYRG8", "target": "JQNL2KII"}, {"source": "XI7CYRG8", "target": "NTUWGCDT"}, {"source": "XI7CYRG8", "target": "ZPTC2EU2"}, {"source": "XI7CYRG8", "target": "6E5KLX6X"}, {"source": "XI7CYRG8", "target": "NNCPUHE6"}, {"source": "XI7CYRG8", "target": "9W67N3W2"}, {"source": "XI7CYRG8", "target": "ADK3L4K5"}, {"source": "XB78ZGFK", "target": "34G9QI8T"}, {"source": "37QKRIYC", "target": "7N4BYR84"}, {"source": "37QKRIYC", "target": "34G9QI8T"}, {"source": "37QKRIYC", "target": "TWSMZCW6"}, {"source": "2LDNCRN4", "target": "F9VLX7PS"}, {"source": "Y4DL944F", "target": "34G9QI8T"}, {"source": "Y4DL944F", "target": "5G4IZVQ8"}, {"source": "Y4DL944F", "target": "YGRIWHW4"}, {"source": "Z52SMZ9I", "target": "FXISQ7ZW"}, {"source": "Z52SMZ9I", "target": "2KXZIYTT"}, {"source": "Z52SMZ9I", "target": "33CHN65F"}, {"source": "67IANJIE", "target": "NTUWGCDT"}, {"source": "67IANJIE", "target": "LS3DVSRL"}, {"source": "67IANJIE", "target": "PN4KZW88"}, {"source": "67IANJIE", "target": "ADK3L4K5"}, {"source": "67IANJIE", "target": "EXENA72Y"}, {"source": "NNCPUHE6", "target": "NTUWGCDT"}, {"source": "NNCPUHE6", "target": "75IT43QT"}, {"source": "NNCPUHE6", "target": "6E5KLX6X"}, {"source": "NNCPUHE6", "target": "3YI7DFW2"}, {"source": "NNCPUHE6", "target": "JMBH9DZ3"}, {"source": "NNCPUHE6", "target": "ADK3L4K5"}, {"source": "VZK6BF78", "target": "NTUWGCDT"}, {"source": "3K2FESNS", "target": "THS8SVYY"}, {"source": "3K2FESNS", "target": "SHZBLVNX"}, {"source": "3K2FESNS", "target": "RPTF5C6P"}, {"source": "J3BRZ59N", "target": "GVLDYG9U"}, {"source": "LBRII9F5", "target": "HLGK973Q"}, {"source": "LBRII9F5", "target": "4VVW4E7R"}, {"source": "LBRII9F5", "target": "6PCTX6BW"}, {"source": "LBRII9F5", "target": "7QGFCBNH"}, {"source": "Z4KN26RY", "target": "V4RID8TN"}, {"source": "Z4KN26RY", "target": "3N9XWYFJ"}, {"source": "Z4KN26RY", "target": "U2ZWMF5Q"}, {"source": "Z4KN26RY", "target": "YGSP98R9"}, {"source": "Z4KN26RY", "target": "4VVW4E7R"}, {"source": "Z4KN26RY", "target": "IPC36S5V"}, {"source": "Z4KN26RY", "target": "LBRII9F5"}, {"source": "Z4KN26RY", "target": "M8IEXC3J"}, {"source": "2CCB2DFF", "target": "RS5DBPDD"}, {"source": "2CCB2DFF", "target": "AN4VBEKF"}, {"source": "2CCB2DFF", "target": "XSVIIP5L"}, {"source": "2CCB2DFF", "target": "FQTXYHMF"}, {"source": "2CCB2DFF", "target": "GJHWZHKJ"}, {"source": "2CCB2DFF", "target": "C44N7NAR"}, {"source": "2CCB2DFF", "target": "I55QRACV"}, {"source": "2CCB2DFF", "target": "WD6EIVIV"}, {"source": "2CCB2DFF", "target": "MRQB7B6N"}, {"source": "2CCB2DFF", "target": "EXE29BH4"}, {"source": "2CCB2DFF", "target": "YQWKSHX5"}, {"source": "AR2BHG9K", "target": "RS5DBPDD"}, {"source": "AR2BHG9K", "target": "EJENTABB"}, {"source": "AR2BHG9K", "target": "AN4VBEKF"}, {"source": "AR2BHG9K", "target": "4VVW4E7R"}, {"source": "AR2BHG9K", "target": "XB6ES2CL"}, {"source": "AR2BHG9K", "target": "WVU5AFQJ"}, {"source": "AR2BHG9K", "target": "Z4KN26RY"}, {"source": "AR2BHG9K", "target": "YQWKSHX5"}, {"source": "FZAUK87U", "target": "U2ZWMF5Q"}, {"source": "AEQHK3PN", "target": "HS2MRUCX"}]}